template_lab3.v
// Template for Northwestern - CompEng 361 - Lab3 -- Version 1.1
// Groupname: Zach Tey, Matias Ketema
// NetIDs: vcs5888, 

// Some useful defines...please add your own
//General Parameters
   `define WORD_WIDTH 32
   `define NUM_REGS 32
//Opcodes
   `define OPCODE_COMPUTE    7'b0110011
   `define OPCODE_BRANCH     7'b1100011
   `define FUNC_BEQ 3'b000
   `define FUNC_BNE 3'b001
   `define FUNC_BLT 3'b100
   `define FUNC_BGE 3'b101
   `define FUNC_BLTU 3'b110
   `define FUNC_BGEU 3'b111
   `define OPCODE_LOAD       7'b0000011
   `define OPCODE_STORE      7'b0100011 
   `define FUNC_ADD      3'b000
   `define AUX_FUNC_ADD  7'b0000000
   `define AUX_FUNC_SUB  7'b0100000
   `define OPCODE_LUI 7'b0110111
   `define OPCODE_AUIPC 7'b0010111
   `define OPCODE_JAL 7'b1101111 
   `define OPCODE_JALR 7'b1100111 
// idk what there are for yet
   `define SIZE_BYTE  2'b00
   `define SIZE_HWORD 2'b01
   `define SIZE_WORD  2'b10

module SingleCycleCPU(halt, clk, rst);
   output halt;
   input clk, rst;

   wire [`WORD_WIDTH-1:0] PC, InstWord;
   wire [`WORD_WIDTH-1:0] DataAddr, StoreData, DataWord;
   wire [1:0]  MemSize;
   wire        MemWrEn;
   
   wire [4:0]  Rsrc1, Rsrc2, Rdst;
   wire [`WORD_WIDTH-1:0] Rdata1, Rdata2, RWrdata;
   wire        RWrEn;
   wire [19:0] imm_u_type;
   wire [6:0] imm_front_s_type;
   wire [4:0] imm_back_s_type; 
   wire [19:0] imm_i_type;
   wire [31:0] imm_j_type;
   wire [31:0] imm_b_type;

   wire [`WORD_WIDTH-1:0] NPC, PC_Plus_4;
   wire [6:0]  opcode;

   wire [6:0]  funct7;
   wire [2:0]  funct3;

   wire invalid_op;
   wire valid_op;
   
   //Inputs/outputs of PC register, MEM, RF; We need to mux them depending on the instruction
   //Don't double drive outputs of mem, reg, ex; They will result in Xs on waveform
   wire [31:0] eu_out;
   wire [6:0] eu_funct7_in;
   wire [2:0] eu_funct3_in;
   wire [31:0] pc_reg_in;

   //Characterize the op-code to its instruction type (R, I, S, U)
   //tbh not sure if this is needed so maybe can delete, but good information to have
   wire [3:0] cur_inst_type;
   parameter R_TYPE = 3'b000;
   parameter I_TYPE = 3'b001;
   parameter S_TYPE = 3'b010;
   parameter U_TYPE = 3'b011;
   parameter B_TYPE = 3'b011;

   //Input Controls to RF, MEM
      //Data
         assign RWrdata = (opcode == `OPCODE_LUI) ? (imm_u_type << 12) :  //lui
                          (opcode == `OPCODE_AUIPC) ? (imm_u_type << 12 + PC) : //auipc 
                          (opcode == `OPCODE_JAL) ? (PC + 4) : 
                          (opcode == `OPCODE_JALR) ? (PC + 4) : 0;              
         assign cur_inst_type = (opcode == `OPCODE_LUI) ? U_TYPE : 0; //not sure if i need this characterization of instruction type
         assign eu_funct7_in = (opcode == `OPCODE_BRANCH && (funct3 == `FUNC_BEQ | funct3 == `FUNC_BNE)) ? `AUX_FUNC_SUB : //beq, bne 
                               (opcode == `OPCODE_BRANCH && (funct3 == `FUNC_BLT | funct3 == `FUNC_BGE | funct3 == `FUNC_BLTU | funct3 == `FUNC_BGEU)) ? `AUX_FUNC_ADD : 0; //blt, bge, bltu, bgeu
         assign eu_funct3_in = (opcode == `OPCODE_BRANCH && (funct3 == `FUNC_BNE)) ? 3'b000 : //bne
                               (opcode == `OPCODE_BRANCH && (funct3 == `FUNC_BLT | funct3 == `FUNC_BGE)) ? 3'b010 : //blt, bge
                               (opcode == `OPCODE_BRANCH && (funct3 == `FUNC_BLTU | funct3 == `FUNC_BGEU)) ? 3'b011 : funct3; //bltu, bgeu
      //Control
         assign RWrEn = (opcode == `OPCODE_LUI) ? 1 : 
                        (opcode == `OPCODE_AUIPC) ? 1 : 
                        (opcode == `OPCODE_JAL) ? 1 : 
                        (opcode == `OPCODE_JALR) ? 1: 0;  
         
   //Halt logic
      // Only support R-TYPE ADD and SUB
   assign halt = !valid_op; //changed this to detect valid_op instead of invalid
   assign invalid_op = !((opcode == `OPCODE_COMPUTE) && (funct3 == `FUNC_ADD) &&
		      ((funct7 == `AUX_FUNC_ADD) || (funct7 == `AUX_FUNC_SUB)));
   assign valid_op = (opcode == `OPCODE_LUI) | (opcode == `OPCODE_AUIPC)|
                     (opcode == `OPCODE_JAL) | (opcode == `OPCODE_JALR) |
                     (opcode == `OPCODE_BRANCH);
     
   // System State 
   Mem   MEM(.InstAddr(PC), .InstOut(InstWord), 
            .DataAddr(DataAddr), .DataSize(MemSize), .DataIn(StoreData), .DataOut(DataWord), .WE(MemWrEn), .CLK(clk));

   RegFile RF(.AddrA(Rsrc1), .DataOutA(Rdata1), 
	      .AddrB(Rsrc2), .DataOutB(Rdata2), 
	      .AddrW(Rdst), .DataInW(RWrdata), .WenW(RWrEn), .CLK(clk));

   Reg PC_REG(.Din(NPC), .Qout(PC), .WE(1'b1), .CLK(clk), .RST(rst));

   // Instruction Decode
   assign opcode = InstWord[6:0];   
   assign Rdst = InstWord[11:7]; 
   assign Rsrc1 = InstWord[19:15]; 
   assign Rsrc2 = InstWord[24:20];
   assign funct3 = InstWord[14:12];  // R-Type, I-Type, S-Type
   assign funct7 = InstWord[31:25];  // R-Type
   assign imm_u_type = InstWord[31:12];
   assign imm_front_s_type = InstWord[32:26];
   assign imm_back_s_type = InstWord[11:7];
   assign imm_i_type = InstWord[31:20]; 
   assign imm_j_type = (opcode == `OPCODE_JALR) ? ((Rdata1 + {{20{InstWord[31]}},InstWord[31:20]}) & 32'hFFFFFFFE) : //jalr
                     (PC + {{11{InstWord[31]}}, InstWord[19:12],InstWord[20], InstWord[30:21],1'b0}); //jal            
   assign imm_b_type = {{19{InstWord[31]}},   
                        InstWord[31],         
                        InstWord[7],          
                        InstWord[30:25],      
                        InstWord[11:8], 
                        1'b0      
                        };
   assign MemWrEn = 1'b0; // Change this to allow stores
   //assign RWrEn = 1'b1;  // At the moment every instruction will write to the register file

   // Hardwired to support R-Type instructions -- please add muxes and other control signals
   ExecutionUnit EU(.out(eu_out), .opA(Rdata1), .opB(Rdata2), .func(eu_funct3_in), .auxFunc(eu_funct7_in));

   // Fetch Address Datapath, notably PC_MEM
   assign PC_Plus_4 = PC + 4;
   assign NPC = ((opcode == `OPCODE_JALR) | (opcode == `OPCODE_JAL)) ? imm_j_type : //jalr, jal
                (opcode == `OPCODE_BRANCH && funct3 == `FUNC_BEQ && eu_out == 0) ? (PC + imm_b_type) : //beq
                (opcode == `OPCODE_BRANCH && funct3 == `FUNC_BNE && eu_out != 0) ? (PC + imm_b_type) : //bne
                (opcode == `OPCODE_BRANCH && (funct3 == `FUNC_BLT | funct3 == `FUNC_BLTU) && eu_out == 1) ? (PC + imm_b_type) : //blt, bltu
                (opcode == `OPCODE_BRANCH && (funct3 == `FUNC_BGE | funct3 == `FUNC_BGEU) && eu_out == 0) ? (PC + imm_b_type) : PC_Plus_4; //bge, bgeu  
endmodule // SingleCycleCPU


// Incomplete version of Lab2 execution unit
// You will need to extend it. Feel free to modify the interface also
module ExecutionUnit(out, opA, opB, func, auxFunc);
   output [`WORD_WIDTH-1:0] out;
   input [`WORD_WIDTH-1:0]  opA, opB;
   input [2:0] 	 func;
   input [6:0] 	 auxFunc;

   // wire [`WORD_WIDTH-1:0] 	 addSub;

   // // Only supports add and subtract
   // assign addSub = (auxFunc == 7'b0100000) ? (opA - opB) : (opA + opB);
   // assign out = (func == 3'b000) ? addSub : 32'hXXXXXXXX;
   
   //Copied over from Zach's Lab 2
   //define operation codes
    localparam OP_ADD = 3'b000; //localparam only exists inside the module
    localparam OP_SUB = 3'b000,
               OP_SLL = 3'b001,
               OP_SLT  = 3'b010,
               OP_SLTU = 3'b011,
               OP_XOR = 3'b100,
               OP_SRL = 3'b101,
               OP_SRA= 3'b101,
               OP_OR = 3'b110,
               OP_AND = 3'b111;
    localparam FUNC_0 = 7'b0000000,
               FUNC_1 = 7'b0100000;

  //Dataflow model
    assign out =
      (func == OP_ADD && auxFunc == FUNC_0) ? (opA + opB) :
      (func == OP_SUB && auxFunc == FUNC_1) ? (opA - opB) :
      (func == OP_SLL && auxFunc == FUNC_0) ? (opA <<  opB[4:0]) :
      (func == OP_SLT && auxFunc == FUNC_0) ? (($signed(opA) <  $signed(opB)) ? 32'd1 : 32'd0) :
      (func == OP_SLTU && auxFunc == FUNC_0) ? ((opA < opB) ? 32'd1 : 32'd0) :
      (func == OP_XOR && auxFunc == FUNC_0) ? (opA ^ opB) :
      (func == OP_SRL && auxFunc == FUNC_0) ? (opA >>  opB[4:0]) :
      (func == OP_SRA && auxFunc == FUNC_1) ? ((opA >> opB[4:0]) | ({32{opA[31]}} << (32 - opB[4:0]))) :
      (func == OP_OR  && auxFunc == FUNC_0) ? (opA | opB) :
      (func == OP_AND && auxFunc == FUNC_0) ? (opA & opB) : 32'b0;

endmodule // ExecutionUnit

lab3_tb.v
// Testbench for Northwestern - CompEng 361 - Lab3 -- Version 1.1
`define CHAR_WIDTH 8
`define MAX_CHAR 80

module tb;
    reg clk, rst;
    reg exit;
    wire halt;
    reg [`CHAR_WIDTH*`MAX_CHAR-1:0] mem_in_fname, mem_out_fname, regs_in_fname, regs_out_fname;
    reg [`CHAR_WIDTH*`MAX_CHAR-1:0] signal_dump_fname;

    // Single Cycle CPU instantiation
    SingleCycleCPU CPU (halt, clk, rst);

    // Clock Period = 10 time units
    always
        #5 clk = ~clk;

    always @(negedge clk)
        if (halt)
            exit = 1;

    initial begin

        // Read commandline options
        if (!$value$plusargs("MEM_IN=%s", mem_in_fname))
            mem_in_fname = "mem_in.hex";
        if (!$value$plusargs("REGS_IN=%s", regs_in_fname))
            regs_in_fname = "regs_in.hex";
        if (!$value$plusargs("REGS_OUT=%s", regs_out_fname))
            regs_out_fname = "regs_out.hex";
        if (!$value$plusargs("MEM_OUT=%s", mem_out_fname))

            mem_out_fname = "mem_out.hex";
         if (!$value$plusargs("DUMP=%s", signal_dump_fname))
            signal_dump_fname = "single.vcd";

        // Clock and reset steup
        #0 rst = 0; exit = 0; clk = 0;
        #0 rst = 1; 
        
        

        // Load program memory and regs
        #0 $readmemh(mem_in_fname, CPU.MEM.Mem);
        #0 $readmemh(regs_in_fname, CPU.RF.Mem);

        // Dumpfile
        $dumpfile(signal_dump_fname);
        $dumpvars();

        // Feel free to modify to inspect whatever you want
        #0 $monitor($time,, "PC=%08x IR=%08x halt=%x exit=%x", CPU.PC, CPU.InstWord, halt, exit);

        // Exit???
        wait(exit);
      
        // Dump memory and regs 
        #0 $writememh(regs_out_fname, CPU.RF.Mem);
        #0 $writememh(mem_out_fname, CPU.MEM.Mem);
        
        $finish;      
   end

endmodule // tb


module Mem(InstAddr, InstOut,
         DataAddr, DataSize, DataIn, DataOut, WE, CLK);
    input [31:0] InstAddr, DataAddr;
    input [1:0] 	DataSize;   
    input [31:0] DataIn;   
    output [31:0] InstOut, DataOut;  
    input      WE, CLK;
    reg [7:0] 	Mem[0:1024];

    wire [31:0] 	DataAddrH, DataAddrW, InstAddrW;

    // Instruction Addresses are word aligned
    assign InstAddrW = InstAddr & 32'hfffffffc;
   
    assign DataAddrH = DataAddr & 32'hfffffffe;
    assign DataAddrW = DataAddr & 32'hfffffffc;

    // Little endian
    assign InstOut = {Mem[InstAddrW+3], Mem[InstAddrW+2], 
		Mem[InstAddrW+1], Mem[InstAddrW]};

    // Little endian
    assign DataOut = (DataSize == 2'b00) ? {4{Mem[DataAddr]}} :
	       ((DataSize == 2'b01) ? {2{Mem[DataAddrH+1],Mem[DataAddrH]}} :
		{Mem[DataAddrW+3], Mem[DataAddrW+2], Mem[DataAddrW+1], Mem[DataAddrW]});
   
     always @ (negedge CLK)
        if (WE) begin
	        case (DataSize)
            2'b00: begin // Write byte
                Mem[DataAddr] <= DataIn[7:0];
            end
            2'b01: begin  // Write halfword
                Mem[DataAddrH] <= DataIn[7:0];
                Mem[DataAddrH+1] <= DataIn[15:8];
            end
            2'b10, 2'b11: begin // Write word
                Mem[DataAddrW] <= DataIn[7:0];
                Mem[DataAddrW+1] <= DataIn[15:8];
                Mem[DataAddrW+2] <= DataIn[23:16];
                Mem[DataAddrW+3] <= DataIn[31:24];
            end
        endcase // case (Size)
     end
endmodule // Mem

module RegFile(AddrA, DataOutA,
	       AddrB, DataOutB,
	       AddrW, DataInW, WenW, CLK);
   input [4:0] AddrA, AddrB, AddrW;
   output [31:0] DataOutA, DataOutB;  
   input [31:0]  DataInW;
   input 	 WenW, CLK;
   reg [31:0] 	 Mem[0:31];
   
   assign DataOutA = (AddrA == 0) ? 32'h00000000 : Mem[AddrA];
   assign DataOutB = (AddrB == 0) ? 32'h00000000 : Mem[AddrB]; 

   always @ (negedge CLK) begin
     if (WenW) begin
       Mem[AddrW] <= DataInW;
     end
      Mem[0] <= 0; // Enforce the invariant that x0 = 0
   end
   
endmodule // RegFile


module Reg(Din, Qout, WE, CLK, RST);
   parameter width = 32;
   parameter init = 0;
   input [width-1:0] Din;
   output [width-1:0] Qout;
   input 	      WE, CLK, RST;

   reg [width-1:0]    Qout;
   
   always @ (negedge CLK or negedge RST)
     if (!RST)
       Qout <= init;
     else
       if (WE)
	     Qout <= Din;
  
endmodule // Reg

single.vcd
$date
	Sat Nov  8 02:21:41 2025
$end
$version
	Icarus Verilog
$end
$timescale
	1s
$end
$scope module tb $end
$var wire 1 ! halt $end
$var reg 1 " clk $end
$var reg 1 # exit $end
$var reg 640 $ mem_in_fname [639:0] $end
$var reg 640 % mem_out_fname [639:0] $end
$var reg 640 & regs_in_fname [639:0] $end
$var reg 640 ' regs_out_fname [639:0] $end
$var reg 1 ( rst $end
$var reg 640 ) signal_dump_fname [639:0] $end
$scope module CPU $end
$var wire 32 * DataAddr [31:0] $end
$var wire 2 + MemSize [1:0] $end
$var wire 1 , MemWrEn $end
$var wire 32 - StoreData [31:0] $end
$var wire 1 " clk $end
$var wire 1 ( rst $end
$var wire 1 . valid_op $end
$var wire 7 / opcode [6:0] $end
$var wire 1 0 invalid_op $end
$var wire 20 1 imm_u_type [19:0] $end
$var wire 32 2 imm_j_type [31:0] $end
$var wire 20 3 imm_i_type [19:0] $end
$var wire 7 4 imm_front_s_type [6:0] $end
$var wire 5 5 imm_back_s_type [4:0] $end
$var wire 32 6 imm_b_type [31:0] $end
$var wire 1 ! halt $end
$var wire 7 7 funct7 [6:0] $end
$var wire 3 8 funct3 [2:0] $end
$var wire 32 9 eu_out [31:0] $end
$var wire 7 : eu_funct7_in [6:0] $end
$var wire 3 ; eu_funct3_in [2:0] $end
$var wire 4 < cur_inst_type [3:0] $end
$var wire 5 = Rsrc2 [4:0] $end
$var wire 5 > Rsrc1 [4:0] $end
$var wire 5 ? Rdst [4:0] $end
$var wire 32 @ Rdata2 [31:0] $end
$var wire 32 A Rdata1 [31:0] $end
$var wire 32 B RWrdata [31:0] $end
$var wire 1 C RWrEn $end
$var wire 32 D PC_Plus_4 [31:0] $end
$var wire 32 E PC [31:0] $end
$var wire 32 F NPC [31:0] $end
$var wire 32 G InstWord [31:0] $end
$var wire 32 H DataWord [31:0] $end
$var parameter 3 I B_TYPE $end
$var parameter 3 J I_TYPE $end
$var parameter 3 K R_TYPE $end
$var parameter 3 L S_TYPE $end
$var parameter 3 M U_TYPE $end
$scope module EU $end
$var wire 7 N auxFunc [6:0] $end
$var wire 3 O func [2:0] $end
$var wire 32 P out [31:0] $end
$var wire 32 Q opB [31:0] $end
$var wire 32 R opA [31:0] $end
$var parameter 7 S FUNC_0 $end
$var parameter 7 T FUNC_1 $end
$var parameter 3 U OP_ADD $end
$var parameter 3 V OP_AND $end
$var parameter 3 W OP_OR $end
$var parameter 3 X OP_SLL $end
$var parameter 3 Y OP_SLT $end
$var parameter 3 Z OP_SLTU $end
$var parameter 3 [ OP_SRA $end
$var parameter 3 \ OP_SRL $end
$var parameter 3 ] OP_SUB $end
$var parameter 3 ^ OP_XOR $end
$upscope $end
$scope module MEM $end
$var wire 1 " CLK $end
$var wire 32 _ DataAddr [31:0] $end
$var wire 32 ` DataAddrH [31:0] $end
$var wire 32 a DataAddrW [31:0] $end
$var wire 32 b DataIn [31:0] $end
$var wire 2 c DataSize [1:0] $end
$var wire 32 d InstAddrW [31:0] $end
$var wire 1 , WE $end
$var wire 32 e InstOut [31:0] $end
$var wire 32 f InstAddr [31:0] $end
$var wire 32 g DataOut [31:0] $end
$upscope $end
$scope module PC_REG $end
$var wire 1 " CLK $end
$var wire 32 h Din [31:0] $end
$var wire 1 ( RST $end
$var wire 1 i WE $end
$var parameter 32 j init $end
$var parameter 32 k width $end
$var reg 32 l Qout [31:0] $end
$upscope $end
$scope module RF $end
$var wire 5 m AddrA [4:0] $end
$var wire 5 n AddrB [4:0] $end
$var wire 5 o AddrW [4:0] $end
$var wire 1 " CLK $end
$var wire 32 p DataInW [31:0] $end
$var wire 1 C WenW $end
$var wire 32 q DataOutB [31:0] $end
$var wire 32 r DataOutA [31:0] $end
$upscope $end
$upscope $end
$upscope $end
$enddefinitions $end
$comment Show the parameter values. $end
$dumpall
b100000 k
b0 j
b100 ^
b0 ]
b101 \
b101 [
b11 Z
b10 Y
b1 X
b110 W
b111 V
b0 U
b100000 T
b0 S
b11 M
b10 L
b0 K
b1 J
b11 I
$end
#0
$dumpvars
b0 r
b0 q
b10010001101000101000000000000 p
b101 o
b11 n
b1000 m
b0 l
1i
b100 h
bx g
b0 f
b10010001101000101001010110111 e
b0 d
bz c
bz b
bx00 a
bx0 `
bz _
b0 R
b0 Q
b0 P
b101 O
b0 N
bx H
b10010001101000101001010110111 G
b100 F
b0 E
b100 D
1C
b10010001101000101000000000000 B
b0 A
b0 @
b101 ?
b1000 >
b11 =
b11 <
b101 ;
b0 :
b0 9
b101 8
b1001 7
b100100100100 6
b101 5
bx000100 4
b100100011 3
b1000101100100100010 2
b10010001101000101 1
10
b110111 /
1.
bz -
0,
bz +
bz *
b1110011011010010110111001100111011011000110010100101110011101100110001101100100 )
1(
b11100100110010101100111011100110101111101101111011101010111010000101110011010000110010101111000 '
b111001001100101011001110111001101011111011010010110111000101110011010000110010101111000 &
b110110101100101011011010101111101101111011101010111010000101110011010000110010101111000 %
b1101101011001010110110101011111011010010110111000101110011010000110010101111000 $
0#
0"
0!
$end
#5
1"
#10
b1 ;
b1 O
b1000 F
b1000 h
1C
b0 <
b10000000000000000 B
b10000000000000000 p
bx000000 4
b0 7
b0 3
b0 =
b0 n
b0 >
b0 m
b1 1
b1 8
b1010 6
b1010 5
b1010 ?
b1010 o
b10111 /
b1010100010111 G
b1010100010111 e
b100 d
b1000000000100 2
b1000 D
b100 E
b100 f
b100 l
0"
#15
1"
#20
b0 ;
b0 O
1C
b100000 F
b100000 h
b11000 3
b11000 =
b11000 n
b1100000000000 1
b0 8
b100000000000 6
b1 5
b1 ?
b1 o
b1101111 /
b1100 B
b1100 p
b1100000000000000011101111 G
b1100000000000000011101111 e
b1000 d
b100000 2
b1100 D
b1000 E
b1000 f
b1000 l
0"
#25
1"
#30
1C
b1100 9
b1100 P
b1100 A
b1100 R
b1100 r
b100100 B
b100100 p
b1100000001000 1
b1 >
b1 m
b10 6
b10 5
b10 ?
b10 o
b1100111 /
b100100 F
b100100 h
b1100000001000000101100111 G
b1100000001000000101100111 e
b100000 d
b100100 2
b100100 D
b100000 E
b100000 f
b100000 l
0"
#35
1"
#40
0C
b11101101110010111011000000000000 9
b11101101110010111011000000000000 P
b101000 F
b101000 h
b100000 :
b100000 N
b0 B
b0 p
b10010001101000101000000000000 @
b10010001101000101000000000000 Q
b10010001101000101000000000000 q
b0 A
b0 R
b0 r
b11000100001001000 2
b1 7
b100101 3
b10010100011000 1
b101 =
b101 n
b11 >
b11 m
b100000 6
b0 5
b0 ?
b0 o
b1100011 /
b10010100011000000001100011 G
b10010100011000000001100011 e
b100100 d
b101000 D
b100100 E
b100100 f
b100100 l
0"
#45
1"
#50
b0 9
b0 P
b1001000 F
b1001000 h
b0 @
b0 Q
b0 q
b100011 3
b11 =
b11 n
b10001100100000 1
b100 >
b100 m
b10001100100000000001100011 G
b10001100100000000001100011 e
b101000 d
b100000100001001010 2
b101100 D
b101000 E
b101000 f
b101000 l
0"
#55
1"
#60
b0 9
b0 P
b10 ;
b10 O
b0 :
b0 N
b1100 @
b1100 Q
b1100 q
b100100 A
b100100 R
b100100 r
b100001 3
b1 =
b1 n
b10 >
b10 m
b10000100010100 1
b100 8
b1001100 F
b1001100 h
b10000100010100000001100011 G
b10000100010100000001100011 e
b1001000 d
b10100100001101000 2
b1001100 D
b1001000 E
b1001000 f
b1001000 l
0"
#65
1"
#70
b1 9
b1 P
b1011100 F
b1011100 h
b100100 @
b100100 Q
b100100 q
b1100 A
b1100 R
b1100 r
b0 7
b10 3
b10 =
b10 n
b10000 6
b10000 5
b1000001100 1
b1 >
b1 m
b10000 ?
b10000 o
b1000001100100001100011 G
b1000001100100001100011 e
b1001100 d
b1100000001001110 2
b1010000 D
b1001100 E
b1001100 f
b1001100 l
0"
#75
1"
#80
b1100000 F
b1100000 h
b10010001101000101000000000000 @
b10010001101000101000000000000 Q
b10010001101000101000000000000 q
b1 7
b100101 3
b101 =
b101 n
b100000 6
b0 5
b10010100001101 1
b101 8
b0 ?
b0 o
b10010100001101000001100011 G
b10010100001101000001100011 e
b1011100 d
b1101100010000000 2
b1100000 D
b1011100 E
b1011100 f
b1011100 l
0"
#85
1"
#90
b1100100 F
b1100100 h
b1 @
b1 Q
b1 q
b11110000000000000000000000000000 A
b11110000000000000000000000000000 R
b11110000000000000000000000000000 r
b0 7
b11111 3
b11111 =
b11111 n
b10000 6
b10000 5
b1111111110101 1
b11110 >
b11110 m
b10000 ?
b10000 o
b1111111110101100001100011 G
b1111111110101100001100011 e
b1100000 d
b11110101100001111110 2
b1100100 D
b1100000 E
b1100000 f
b1100000 l
0"
#95
1"
#100
b0 9
b0 P
b11 ;
b11 O
b1110100 F
b1110100 h
b1111111110111 1
b111 8
b1111111110111100001100011 G
b1111111110111100001100011 e
b1100100 d
b11110111100010000010 2
b1101000 D
b1100100 E
b1100100 f
b1100100 l
0"
#105
1"
#110
b1 9
b1 P
b10000100 F
b10000100 h
b11111111000000000000000000000000 @
b11111111000000000000000000000000 Q
b11111111000000000000000000000000 q
b10001 A
b10001 R
b10001 r
b11101 3
b11101 =
b11101 n
b11100 >
b11100 m
b1110111100110 1
b110 8
b1110111100110100001100011 G
b1110111100110100001100011 e
b1110100 d
b11100110100010010000 2
b1111000 D
b1110100 E
b1110100 f
b1110100 l
0"
#115
1"
#120
b0 9
b0 P
b10 ;
b10 O
b10001000 F
b10001000 h
b1110111100100 1
b100 8
b1110111100100100001100011 G
b1110111100100100001100011 e
b10000100 d
b11100100100010100000 2
b10001000 D
b10000100 E
b10000100 f
b10000100 l
0"
#125
1"
#130
b0 ;
b0 O
b10001100 F
b10001100 h
b0 @
b0 Q
b0 q
b0 A
b0 R
b0 r
1!
0.
b0 3
b0 =
b0 n
b0 >
b0 m
b0 6
b0 5
b0 1
b0 8
b0 ?
b0 o
b1110011 /
b1110011 G
b1110011 e
b10001000 d
b10001000 2
b10001100 D
b10001000 E
b10001000 f
b10001000 l
0"
#135
1"
#140
bx ;
bx O
bx0000x00x0000 B
bx0000x00x0000 p
bx 9
bx P
bx F
bx h
x0
xC
b0x00000 :
b0x00000 N
bx @
bx Q
bx q
bx A
bx R
bx r
x!
x.
b0xx <
bx 4
bx 7
b0xxxxxxxxxxxx 3
bx =
bx n
bx 1
bx 8
bx >
bx m
bx0 6
bx 5
bx ?
bx o
bx /
bx G
bx e
b10001100 d
bx 2
b10010000 D
b10001100 E
b10001100 f
b10001100 l
1#
0"
