template_lab3.v
// Template for Northwestern - CompEng 361 - Lab3 -- Version 1.1
// Groupname: Zach Tey, Matias Ketema
// NetIDs: vcs5888, 

// Some useful defines...please add your own
//General Parameters
   `define WORD_WIDTH 32
   `define NUM_REGS 32
//Opcodes
   `define OPCODE_COMPUTE    7'b0110011
   `define OPCODE_BRANCH     7'b1100011
   `define FUNC_BEQ 3'b000
   `define FUNC_BNE 3'b001
   `define FUNC_BLT 3'b100
   `define FUNC_BGE 3'b101
   `define FUNC_BLTU 3'b110
   `define FUNC_BGEU 3'b111
   `define OPCODE_LOAD       7'b0000011
   `define FUNC_LB 3'b000
   `define FUNC_LH 3'b001
   `define FUNC_LW 3'b010
   `define FUNC_LBU 3'b100
   `define FUNC_LHU 3'b101
   `define OPCODE_STORE      7'b0100011 
   `define FUNC_ADD      3'b000
   `define AUX_FUNC_ADD  7'b0000000
   `define AUX_FUNC_SUB  7'b0100000
   `define OPCODE_LUI 7'b0110111
   `define OPCODE_AUIPC 7'b0010111
   `define OPCODE_JAL 7'b1101111 
   `define OPCODE_JALR 7'b1100111 
// idk what there are for yet
   `define SIZE_BYTE  2'b00
   `define SIZE_HWORD 2'b01
   `define SIZE_WORD  2'b10

module SingleCycleCPU(halt, clk, rst);
   output halt;
   input clk, rst;

   wire [`WORD_WIDTH-1:0] PC, InstWord;
   wire [`WORD_WIDTH-1:0] DataAddr, StoreData, DataWord;
   wire [1:0]  MemSize;
   wire        MemWrEn;
   
   wire [4:0]  Rsrc1, Rsrc2, Rdst;
   wire [`WORD_WIDTH-1:0] Rdata1, Rdata2, RWrdata;
   wire        RWrEn;
   wire [19:0] imm_u_type;
   wire [6:0] imm_front_s_type;
   wire [4:0] imm_back_s_type; 
   wire [19:0] imm_i_type;
   wire [31:0] imm_j_type;
   wire [31:0] imm_b_type;

   wire [`WORD_WIDTH-1:0] NPC, PC_Plus_4;
   wire [6:0]  opcode;

   wire [6:0]  funct7;
   wire [2:0]  funct3;

   wire invalid_op;
   wire valid_op;
   
   //Inputs/outputs of PC register, MEM, RF; We need to mux them depending on the instruction
   //Don't double drive outputs of mem, reg, ex; They will result in Xs on waveform
   wire [31:0] eu_out;
   wire [6:0] eu_funct7_in;
   wire [2:0] eu_funct3_in;
   wire [31:0] pc_reg_in;
   wire [31:0] Rdata2_in;

   //Characterize the op-code to its instruction type (R, I, S, U)
   //tbh not sure if this is needed so maybe can delete, but good information to have
   wire [3:0] cur_inst_type;
   parameter R_TYPE = 3'b000;
   parameter I_TYPE = 3'b001;
   parameter S_TYPE = 3'b010;
   parameter U_TYPE = 3'b011;
   parameter B_TYPE = 3'b011;

   //Input Controls to RF, MEM
      //Data
         assign RWrdata = (opcode == `OPCODE_LUI) ? (imm_u_type << 12) :  //lui
                          (opcode == `OPCODE_AUIPC) ? (imm_u_type << 12 + PC) : //auipc 
                          (opcode == `OPCODE_JAL) ? (PC + 4) : //jal
                          (opcode == `OPCODE_JALR) ? (PC + 4) : //jalr
                          (opcode ==  `OPCODE_LOAD && (funct3 == `FUNC_LB)) ? {{24{DataWord[7]}}, DataWord[7:0]} : //lb
                          (opcode ==  `OPCODE_LOAD && (funct3 == `FUNC_LH)) ? {{16{DataWord[15]}}, DataWord[15:0]} : //lh  
                          (opcode ==  `OPCODE_LOAD && (funct3 == `FUNC_LW)) ? DataWord : //lw  
                          (opcode ==  `OPCODE_LOAD && (funct3 == `FUNC_LBU)) ? {{24{1'b0}}, DataWord[7:0]} : //lbu   
                          (opcode ==  `OPCODE_LOAD && (funct3 == `FUNC_LHU)) ? {{16{1'b0}}, DataWord[15:0]} :0; //lhu        
         assign cur_inst_type = (opcode == `OPCODE_LUI) ? U_TYPE : 0; //not sure if i need this characterization of instruction type
         assign eu_funct7_in = (opcode == `OPCODE_BRANCH && (funct3 == `FUNC_BEQ | funct3 == `FUNC_BNE)) ? `AUX_FUNC_SUB : //beq, bne 
                               (opcode == `OPCODE_BRANCH && (funct3 == `FUNC_BLT | funct3 == `FUNC_BGE | funct3 == `FUNC_BLTU | funct3 == `FUNC_BGEU)) ? `AUX_FUNC_ADD : 0; //blt, bge, bltu, bgeu
         assign eu_funct3_in = (opcode == `OPCODE_BRANCH && (funct3 == `FUNC_BNE)) ? 3'b000 : //bne
                               (opcode == `OPCODE_BRANCH && (funct3 == `FUNC_BLT | funct3 == `FUNC_BGE)) ? 3'b010 : //blt, bge
                               (opcode == `OPCODE_BRANCH && (funct3 == `FUNC_BLTU | funct3 == `FUNC_BGEU)) ? 3'b011 : //bltu, bgeu
                               (opcode == `OPCODE_LOAD && (funct3 == `FUNC_LB | funct3 == `FUNC_LH | funct3 == `FUNC_LW | funct3 == `FUNC_LBU | funct3 == `FUNC_LHU)) ? 3'b000: funct3; //lb, lh, lw, lbu, lhu 
         assign Rdata2_in = (opcode ==  `OPCODE_LOAD && (funct3 == `FUNC_LB | funct3 == `FUNC_LH | funct3 == `FUNC_LW | funct3 == `FUNC_LBU | funct3 == `FUNC_LHU)) ? {{20{imm_i_type[11]}},imm_i_type} : Rdata2; //lb, lh, lw, lbu, lhu
         assign DataAddr = (opcode ==  `OPCODE_LOAD && (funct3 == `FUNC_LB | funct3 == `FUNC_LH | funct3 == `FUNC_LW | funct3 == `FUNC_LBU | funct3 == `FUNC_LHU)) ? (eu_out) : 0; //lb, lh, lw, lbu, lhu
         assign MemSize = (opcode ==  `OPCODE_LOAD && (funct3 == `FUNC_LB | funct3 == `FUNC_LBU)) ? 2'b00 : //lb, lbu
                          (opcode ==  `OPCODE_LOAD && (funct3 == `FUNC_LH | funct3 == `FUNC_LHU)) ? 2'b01 : //lh, lhu
                          (opcode ==  `OPCODE_LOAD && (funct3 == `FUNC_LW)) ? 2'b10 : 0; //lw

      //Control
         assign RWrEn = (opcode == `OPCODE_LUI) ? 1 : 
                        (opcode == `OPCODE_AUIPC) ? 1 : 
                        (opcode == `OPCODE_JAL) ? 1 : 
                        (opcode == `OPCODE_JALR) ? 1: 
                        (opcode == `OPCODE_LOAD) ? 1: 0;  
         assign MemWrEn = 0; //load instructions

         
   //Halt logic
      // Only support R-TYPE ADD and SUB
   assign halt = !valid_op; //changed this to detect valid_op instead of invalid
   assign invalid_op = !((opcode == `OPCODE_COMPUTE) && (funct3 == `FUNC_ADD) &&
		      ((funct7 == `AUX_FUNC_ADD) || (funct7 == `AUX_FUNC_SUB)));
   assign valid_op = (opcode == `OPCODE_LUI) | (opcode == `OPCODE_AUIPC)|
                     (opcode == `OPCODE_JAL) | (opcode == `OPCODE_JALR) |
                     (opcode == `OPCODE_BRANCH) | (opcode == `OPCODE_LOAD);
     
   // System State 
   Mem   MEM(.InstAddr(PC), .InstOut(InstWord), 
            .DataAddr(DataAddr), .DataSize(MemSize), .DataIn(StoreData), .DataOut(DataWord), .WE(MemWrEn), .CLK(clk));

   RegFile RF(.AddrA(Rsrc1), .DataOutA(Rdata1), 
	      .AddrB(Rsrc2), .DataOutB(Rdata2), 
	      .AddrW(Rdst), .DataInW(RWrdata), .WenW(RWrEn), .CLK(clk));

   Reg PC_REG(.Din(NPC), .Qout(PC), .WE(1'b1), .CLK(clk), .RST(rst));

   // Instruction Decode
   assign opcode = InstWord[6:0];   
   assign Rdst = InstWord[11:7]; 
   assign Rsrc1 = InstWord[19:15]; 
   assign Rsrc2 = InstWord[24:20];
   assign funct3 = InstWord[14:12];  // R-Type, I-Type, S-Type
   assign funct7 = InstWord[31:25];  // R-Type
   assign imm_u_type = InstWord[31:12];
   assign imm_front_s_type = InstWord[32:26];
   assign imm_back_s_type = InstWord[11:7];
   assign imm_i_type = InstWord[31:20]; 
   assign imm_j_type = (opcode == `OPCODE_JALR) ? ((Rdata1 + {{20{InstWord[31]}},InstWord[31:20]}) & 32'hFFFFFFFE) : //jalr
                     (PC + {{11{InstWord[31]}}, InstWord[19:12],InstWord[20], InstWord[30:21],1'b0}); //jal            
   assign imm_b_type = {{19{InstWord[31]}},   
                        InstWord[31],         
                        InstWord[7],          
                        InstWord[30:25],      
                        InstWord[11:8], 
                        1'b0      
                        };
   //assign MemWrEn = 1'b0; // Change this to allow stores
   //assign RWrEn = 1'b1;  // At the moment every instruction will write to the register file

   // Hardwired to support R-Type instructions -- please add muxes and other control signals
   ExecutionUnit EU(.out(eu_out), .opA(Rdata1), .opB(Rdata2_in), .func(eu_funct3_in), .auxFunc(eu_funct7_in));

   // Fetch Address Datapath, notably PC_MEM
   assign PC_Plus_4 = PC + 4;
   assign NPC = ((opcode == `OPCODE_JALR) | (opcode == `OPCODE_JAL)) ? imm_j_type : //jalr, jal
                (opcode == `OPCODE_BRANCH && funct3 == `FUNC_BEQ && eu_out == 0) ? (PC + imm_b_type) : //beq
                (opcode == `OPCODE_BRANCH && funct3 == `FUNC_BNE && eu_out != 0) ? (PC + imm_b_type) : //bne
                (opcode == `OPCODE_BRANCH && (funct3 == `FUNC_BLT | funct3 == `FUNC_BLTU) && eu_out == 1) ? (PC + imm_b_type) : //blt, bltu
                (opcode == `OPCODE_BRANCH && (funct3 == `FUNC_BGE | funct3 == `FUNC_BGEU) && eu_out == 0) ? (PC + imm_b_type) : PC_Plus_4; //bge, bgeu  
endmodule // SingleCycleCPU


// Incomplete version of Lab2 execution unit
// You will need to extend it. Feel free to modify the interface also
module ExecutionUnit(out, opA, opB, func, auxFunc);
   output [`WORD_WIDTH-1:0] out;
   input [`WORD_WIDTH-1:0]  opA, opB;
   input [2:0] 	 func;
   input [6:0] 	 auxFunc;

   // wire [`WORD_WIDTH-1:0] 	 addSub;

   // // Only supports add and subtract
   // assign addSub = (auxFunc == 7'b0100000) ? (opA - opB) : (opA + opB);
   // assign out = (func == 3'b000) ? addSub : 32'hXXXXXXXX;
   
   //Copied over from Zach's Lab 2
   //define operation codes
    localparam OP_ADD = 3'b000; //localparam only exists inside the module
    localparam OP_SUB = 3'b000,
               OP_SLL = 3'b001,
               OP_SLT  = 3'b010,
               OP_SLTU = 3'b011,
               OP_XOR = 3'b100,
               OP_SRL = 3'b101,
               OP_SRA= 3'b101,
               OP_OR = 3'b110,
               OP_AND = 3'b111;
    localparam FUNC_0 = 7'b0000000,
               FUNC_1 = 7'b0100000;

  //Dataflow model
    assign out =
      (func == OP_ADD && auxFunc == FUNC_0) ? (opA + opB) :
      (func == OP_SUB && auxFunc == FUNC_1) ? (opA - opB) :
      (func == OP_SLL && auxFunc == FUNC_0) ? (opA <<  opB[4:0]) :
      (func == OP_SLT && auxFunc == FUNC_0) ? (($signed(opA) <  $signed(opB)) ? 32'd1 : 32'd0) :
      (func == OP_SLTU && auxFunc == FUNC_0) ? ((opA < opB) ? 32'd1 : 32'd0) :
      (func == OP_XOR && auxFunc == FUNC_0) ? (opA ^ opB) :
      (func == OP_SRL && auxFunc == FUNC_0) ? (opA >>  opB[4:0]) :
      (func == OP_SRA && auxFunc == FUNC_1) ? ((opA >> opB[4:0]) | ({32{opA[31]}} << (32 - opB[4:0]))) :
      (func == OP_OR  && auxFunc == FUNC_0) ? (opA | opB) :
      (func == OP_AND && auxFunc == FUNC_0) ? (opA & opB) : 32'b0;

endmodule // ExecutionUnit

lab3_tb.v
// Testbench for Northwestern - CompEng 361 - Lab3 -- Version 1.1
`define CHAR_WIDTH 8
`define MAX_CHAR 80

module tb;
    reg clk, rst;
    reg exit;
    wire halt;
    reg [`CHAR_WIDTH*`MAX_CHAR-1:0] mem_in_fname, mem_out_fname, regs_in_fname, regs_out_fname;
    reg [`CHAR_WIDTH*`MAX_CHAR-1:0] signal_dump_fname;

    // Single Cycle CPU instantiation
    SingleCycleCPU CPU (halt, clk, rst);

    // Clock Period = 10 time units
    always
        #5 clk = ~clk;

    always @(negedge clk)
        if (halt)
            exit = 1;

    initial begin

        // Read commandline options
        if (!$value$plusargs("MEM_IN=%s", mem_in_fname))
            mem_in_fname = "mem_in.hex";
        if (!$value$plusargs("REGS_IN=%s", regs_in_fname))
            regs_in_fname = "regs_in.hex";
        if (!$value$plusargs("REGS_OUT=%s", regs_out_fname))
            regs_out_fname = "regs_out.hex";
        if (!$value$plusargs("MEM_OUT=%s", mem_out_fname))

            mem_out_fname = "mem_out.hex";
         if (!$value$plusargs("DUMP=%s", signal_dump_fname))
            signal_dump_fname = "single.vcd";

        // Clock and reset steup
        #0 rst = 0; exit = 0; clk = 0;
        #0 rst = 1; 
        
        

        // Load program memory and regs
        #0 $readmemh(mem_in_fname, CPU.MEM.Mem);
        #0 $readmemh(regs_in_fname, CPU.RF.Mem);

        // Dumpfile
        $dumpfile(signal_dump_fname);
        $dumpvars();

        // Feel free to modify to inspect whatever you want
        #0 $monitor($time,, "PC=%08x IR=%08x halt=%x exit=%x", CPU.PC, CPU.InstWord, halt, exit);

        // Exit???
        wait(exit);
      
        // Dump memory and regs 
        #0 $writememh(regs_out_fname, CPU.RF.Mem);
        #0 $writememh(mem_out_fname, CPU.MEM.Mem);
        
        $finish;      
   end

endmodule // tb


module Mem(InstAddr, InstOut,
         DataAddr, DataSize, DataIn, DataOut, WE, CLK);
    input [31:0] InstAddr, DataAddr;
    input [1:0] 	DataSize;   
    input [31:0] DataIn;   
    output [31:0] InstOut, DataOut;  
    input      WE, CLK;
    reg [7:0] 	Mem[0:1024];

    wire [31:0] 	DataAddrH, DataAddrW, InstAddrW;

    // Instruction Addresses are word aligned
    assign InstAddrW = InstAddr & 32'hfffffffc;
   
    assign DataAddrH = DataAddr & 32'hfffffffe;
    assign DataAddrW = DataAddr & 32'hfffffffc;

    // Little endian
    assign InstOut = {Mem[InstAddrW+3], Mem[InstAddrW+2], 
		Mem[InstAddrW+1], Mem[InstAddrW]};

    // Little endian
    assign DataOut = (DataSize == 2'b00) ? {4{Mem[DataAddr]}} :
	       ((DataSize == 2'b01) ? {2{Mem[DataAddrH+1],Mem[DataAddrH]}} :
		{Mem[DataAddrW+3], Mem[DataAddrW+2], Mem[DataAddrW+1], Mem[DataAddrW]});
   
     always @ (negedge CLK)
        if (WE) begin
	        case (DataSize)
            2'b00: begin // Write byte
                Mem[DataAddr] <= DataIn[7:0];
            end
            2'b01: begin  // Write halfword
                Mem[DataAddrH] <= DataIn[7:0];
                Mem[DataAddrH+1] <= DataIn[15:8];
            end
            2'b10, 2'b11: begin // Write word
                Mem[DataAddrW] <= DataIn[7:0];
                Mem[DataAddrW+1] <= DataIn[15:8];
                Mem[DataAddrW+2] <= DataIn[23:16];
                Mem[DataAddrW+3] <= DataIn[31:24];
            end
        endcase // case (Size)
     end
endmodule // Mem

module RegFile(AddrA, DataOutA,
	       AddrB, DataOutB,
	       AddrW, DataInW, WenW, CLK);
   input [4:0] AddrA, AddrB, AddrW;
   output [31:0] DataOutA, DataOutB;  
   input [31:0]  DataInW;
   input 	 WenW, CLK;
   reg [31:0] 	 Mem[0:31];
   
   assign DataOutA = (AddrA == 0) ? 32'h00000000 : Mem[AddrA];
   assign DataOutB = (AddrB == 0) ? 32'h00000000 : Mem[AddrB]; 

   always @ (negedge CLK) begin
     if (WenW) begin
       Mem[AddrW] <= DataInW;
     end
      Mem[0] <= 0; // Enforce the invariant that x0 = 0
   end
   
endmodule // RegFile


module Reg(Din, Qout, WE, CLK, RST);
   parameter width = 32;
   parameter init = 0;
   input [width-1:0] Din;
   output [width-1:0] Qout;
   input 	      WE, CLK, RST;

   reg [width-1:0]    Qout;
   
   always @ (negedge CLK or negedge RST)
     if (!RST)
       Qout <= init;
     else
       if (WE)
	     Qout <= Din;
  
endmodule // Reg

single.vcd
$date
	Sat Nov  8 18:27:58 2025
$end
$version
	Icarus Verilog
$end
$timescale
	1s
$end
$scope module tb $end
$var wire 1 ! halt $end
$var reg 1 " clk $end
$var reg 1 # exit $end
$var reg 640 $ mem_in_fname [639:0] $end
$var reg 640 % mem_out_fname [639:0] $end
$var reg 640 & regs_in_fname [639:0] $end
$var reg 640 ' regs_out_fname [639:0] $end
$var reg 1 ( rst $end
$var reg 640 ) signal_dump_fname [639:0] $end
$scope module CPU $end
$var wire 1 * MemWrEn $end
$var wire 32 + StoreData [31:0] $end
$var wire 1 " clk $end
$var wire 1 ( rst $end
$var wire 1 , valid_op $end
$var wire 7 - opcode [6:0] $end
$var wire 1 . invalid_op $end
$var wire 20 / imm_u_type [19:0] $end
$var wire 32 0 imm_j_type [31:0] $end
$var wire 20 1 imm_i_type [19:0] $end
$var wire 7 2 imm_front_s_type [6:0] $end
$var wire 5 3 imm_back_s_type [4:0] $end
$var wire 32 4 imm_b_type [31:0] $end
$var wire 1 ! halt $end
$var wire 7 5 funct7 [6:0] $end
$var wire 3 6 funct3 [2:0] $end
$var wire 32 7 eu_out [31:0] $end
$var wire 7 8 eu_funct7_in [6:0] $end
$var wire 3 9 eu_funct3_in [2:0] $end
$var wire 4 : cur_inst_type [3:0] $end
$var wire 5 ; Rsrc2 [4:0] $end
$var wire 5 < Rsrc1 [4:0] $end
$var wire 5 = Rdst [4:0] $end
$var wire 32 > Rdata2_in [31:0] $end
$var wire 32 ? Rdata2 [31:0] $end
$var wire 32 @ Rdata1 [31:0] $end
$var wire 32 A RWrdata [31:0] $end
$var wire 1 B RWrEn $end
$var wire 32 C PC_Plus_4 [31:0] $end
$var wire 32 D PC [31:0] $end
$var wire 32 E NPC [31:0] $end
$var wire 2 F MemSize [1:0] $end
$var wire 32 G InstWord [31:0] $end
$var wire 32 H DataWord [31:0] $end
$var wire 32 I DataAddr [31:0] $end
$var parameter 3 J B_TYPE $end
$var parameter 3 K I_TYPE $end
$var parameter 3 L R_TYPE $end
$var parameter 3 M S_TYPE $end
$var parameter 3 N U_TYPE $end
$scope module EU $end
$var wire 7 O auxFunc [6:0] $end
$var wire 3 P func [2:0] $end
$var wire 32 Q opB [31:0] $end
$var wire 32 R out [31:0] $end
$var wire 32 S opA [31:0] $end
$var parameter 7 T FUNC_0 $end
$var parameter 7 U FUNC_1 $end
$var parameter 3 V OP_ADD $end
$var parameter 3 W OP_AND $end
$var parameter 3 X OP_OR $end
$var parameter 3 Y OP_SLL $end
$var parameter 3 Z OP_SLT $end
$var parameter 3 [ OP_SLTU $end
$var parameter 3 \ OP_SRA $end
$var parameter 3 ] OP_SRL $end
$var parameter 3 ^ OP_SUB $end
$var parameter 3 _ OP_XOR $end
$upscope $end
$scope module MEM $end
$var wire 1 " CLK $end
$var wire 32 ` DataAddr [31:0] $end
$var wire 32 a DataAddrH [31:0] $end
$var wire 32 b DataAddrW [31:0] $end
$var wire 32 c DataIn [31:0] $end
$var wire 2 d DataSize [1:0] $end
$var wire 32 e InstAddrW [31:0] $end
$var wire 1 * WE $end
$var wire 32 f InstOut [31:0] $end
$var wire 32 g InstAddr [31:0] $end
$var wire 32 h DataOut [31:0] $end
$upscope $end
$scope module PC_REG $end
$var wire 1 " CLK $end
$var wire 32 i Din [31:0] $end
$var wire 1 ( RST $end
$var wire 1 j WE $end
$var parameter 32 k init $end
$var parameter 32 l width $end
$var reg 32 m Qout [31:0] $end
$upscope $end
$scope module RF $end
$var wire 5 n AddrA [4:0] $end
$var wire 5 o AddrB [4:0] $end
$var wire 5 p AddrW [4:0] $end
$var wire 1 " CLK $end
$var wire 32 q DataInW [31:0] $end
$var wire 1 B WenW $end
$var wire 32 r DataOutB [31:0] $end
$var wire 32 s DataOutA [31:0] $end
$upscope $end
$upscope $end
$upscope $end
$enddefinitions $end
$comment Show the parameter values. $end
$dumpall
b100000 l
b0 k
b100 _
b0 ^
b101 ]
b101 \
b11 [
b10 Z
b1 Y
b110 X
b111 W
b0 V
b100000 U
b0 T
b11 N
b10 M
b0 L
b1 K
b11 J
$end
#0
$dumpvars
b0 s
b0 r
b10010001101000101000000000000 q
b101 p
b11 o
b1000 n
b0 m
1j
b100 i
b10110111101101111011011110110111 h
b0 g
b10010001101000101001010110111 f
b0 e
b0 d
bz c
b0 b
b0 a
b0 `
b0 S
b0 R
b0 Q
b101 P
b0 O
b0 I
b10110111101101111011011110110111 H
b10010001101000101001010110111 G
b0 F
b100 E
b0 D
b100 C
1B
b10010001101000101000000000000 A
b0 @
b0 ?
b0 >
b101 =
b1000 <
b11 ;
b11 :
b101 9
b0 8
b0 7
b101 6
b1001 5
b100100100100 4
b101 3
bx000100 2
b100100011 1
b1000101100100100010 0
b10010001101000101 /
1.
b110111 -
1,
bz +
0*
b1110011011010010110111001100111011011000110010100101110011101100110001101100100 )
1(
b11100100110010101100111011100110101111101101111011101010111010000101110011010000110010101111000 '
b111001001100101011001110111001101011111011010010110111000101110011010000110010101111000 &
b110110101100101011011010101111101101111011101010111010000101110011010000110010101111000 %
b1101101011001010110110101011111011010010110111000101110011010000110010101111000 $
0#
0"
0!
$end
#5
1"
#10
b1 9
b1 P
b1000 E
b1000 i
1B
b0 :
b10000000000000000 A
b10000000000000000 q
bx000000 2
b0 5
b0 1
b0 ;
b0 o
b0 <
b0 n
b1 /
b1 6
b1010 4
b1010 3
b1010 =
b1010 p
b10111 -
b1010100010111 G
b1010100010111 f
b100 e
b1000000000100 0
b1000 C
b100 D
b100 g
b100 m
0"
#15
1"
#20
b0 9
b0 P
1B
b100000 E
b100000 i
b11000 1
b11000 ;
b11000 o
b1100000000000 /
b0 6
b100000000000 4
b1 3
b1 =
b1 p
b1101111 -
b1100 A
b1100 q
b1100000000000000011101111 G
b1100000000000000011101111 f
b1000 e
b100000 0
b1100 C
b1000 D
b1000 g
b1000 m
0"
#25
1"
#30
1B
b1100 7
b1100 R
b1100 @
b1100 S
b1100 s
b100100 A
b100100 q
b1100000001000 /
b1 <
b1 n
b10 4
b10 3
b10 =
b10 p
b1100111 -
b100100 E
b100100 i
b1100000001000000101100111 G
b1100000001000000101100111 f
b100000 e
b100100 0
b100100 C
b100000 D
b100000 g
b100000 m
0"
#35
1"
#40
0B
b10010001101000101000000000000 >
b10010001101000101000000000000 Q
b11101101110010111011000000000000 7
b11101101110010111011000000000000 R
b101000 E
b101000 i
b100000 8
b100000 O
b0 A
b0 q
b10010001101000101000000000000 ?
b10010001101000101000000000000 r
b0 @
b0 S
b0 s
b11000100001001000 0
b1 5
b100101 1
b10010100011000 /
b101 ;
b101 o
b11 <
b11 n
b100000 4
b0 3
b0 =
b0 p
b1100011 -
b10010100011000000001100011 G
b10010100011000000001100011 f
b100100 e
b101000 C
b100100 D
b100100 g
b100100 m
0"
#45
1"
#50
b0 7
b0 R
b0 >
b0 Q
b1001000 E
b1001000 i
b0 ?
b0 r
b100011 1
b11 ;
b11 o
b10001100100000 /
b100 <
b100 n
b10001100100000000001100011 G
b10001100100000000001100011 f
b101000 e
b100000100001001010 0
b101100 C
b101000 D
b101000 g
b101000 m
0"
#55
1"
#60
b10 9
b10 P
b1100 >
b1100 Q
b0 7
b0 R
b0 8
b0 O
b1100 ?
b1100 r
b100100 @
b100100 S
b100100 s
b100001 1
b1 ;
b1 o
b10 <
b10 n
b10000100010100 /
b100 6
b1001100 E
b1001100 i
b10000100010100000001100011 G
b10000100010100000001100011 f
b1001000 e
b10100100001101000 0
b1001100 C
b1001000 D
b1001000 g
b1001000 m
0"
#65
1"
#70
b1 7
b1 R
b100100 >
b100100 Q
b1011100 E
b1011100 i
b100100 ?
b100100 r
b1100 @
b1100 S
b1100 s
b0 5
b10 1
b10 ;
b10 o
b10000 4
b10000 3
b1000001100 /
b1 <
b1 n
b10000 =
b10000 p
b1000001100100001100011 G
b1000001100100001100011 f
b1001100 e
b1100000001001110 0
b1010000 C
b1001100 D
b1001100 g
b1001100 m
0"
#75
1"
#80
b10010001101000101000000000000 >
b10010001101000101000000000000 Q
b1100000 E
b1100000 i
b10010001101000101000000000000 ?
b10010001101000101000000000000 r
b1 5
b100101 1
b101 ;
b101 o
b100000 4
b0 3
b10010100001101 /
b101 6
b0 =
b0 p
b10010100001101000001100011 G
b10010100001101000001100011 f
b1011100 e
b1101100010000000 0
b1100000 C
b1011100 D
b1011100 g
b1011100 m
0"
#85
1"
#90
b1 >
b1 Q
b1100100 E
b1100100 i
b1 ?
b1 r
b11110000000000000000000000000000 @
b11110000000000000000000000000000 S
b11110000000000000000000000000000 s
b0 5
b11111 1
b11111 ;
b11111 o
b10000 4
b10000 3
b1111111110101 /
b11110 <
b11110 n
b10000 =
b10000 p
b1111111110101100001100011 G
b1111111110101100001100011 f
b1100000 e
b11110101100001111110 0
b1100100 C
b1100000 D
b1100000 g
b1100000 m
0"
#95
1"
#100
b0 7
b0 R
b11 9
b11 P
b1110100 E
b1110100 i
b1111111110111 /
b111 6
b1111111110111100001100011 G
b1111111110111100001100011 f
b1100100 e
b11110111100010000010 0
b1101000 C
b1100100 D
b1100100 g
b1100100 m
0"
#105
1"
#110
b1 7
b1 R
b11111111000000000000000000000000 >
b11111111000000000000000000000000 Q
b10000100 E
b10000100 i
b11111111000000000000000000000000 ?
b11111111000000000000000000000000 r
b10001 @
b10001 S
b10001 s
b11101 1
b11101 ;
b11101 o
b11100 <
b11100 n
b1110111100110 /
b110 6
b1110111100110100001100011 G
b1110111100110100001100011 f
b1110100 e
b11100110100010010000 0
b1111000 C
b1110100 D
b1110100 g
b1110100 m
0"
#115
1"
#120
b0 7
b0 R
b10 9
b10 P
b10001000 E
b10001000 i
b1110111100100 /
b100 6
b1110111100100100001100011 G
b1110111100100100001100011 f
b10000100 e
b11100100100010100000 0
b10001000 C
b10000100 D
b10000100 g
b10000100 m
0"
#125
1"
#130
b1100100 a
b1100100 b
b1100011011000110110001101100011 H
b1100011011000110110001101100011 h
b1100100 I
b1100100 `
b1100100 7
b1100100 R
1B
b1100011 A
b1100011 q
b101 >
b101 Q
b0 9
b0 P
b10001100 E
b10001100 i
b10010001101000101000000000000 ?
b10010001101000101000000000000 r
b1011111 @
b1011111 S
b1011111 s
b101 1
b101 ;
b101 o
b10111011000 /
b0 6
b11011 <
b11011 n
b100000000110 4
b111 3
b111 =
b111 p
b11 -
b10111011000001110000011 G
b10111011000001110000011 f
b10001000 e
b11011000100010001100 0
b10001100 C
b10001000 D
b10001000 g
b10001000 m
0"
#135
1"
#140
b111100001100011 A
b111100001100011 q
b1111000011000110111100001100011 H
b1111000011000110111100001100011 h
b1 F
b1 d
b10010000 E
b10010000 i
b10111011001 /
b1 6
b1000 4
b1000 3
b1000 =
b1000 p
b10111011001010000000011 G
b10111011001010000000011 f
b10001100 e
b11011001100010010000 0
b10010000 C
b10001100 D
b10001100 g
b10001100 m
0"
#145
1"
#150
b1111111110111100001100011 A
b1111111110111100001100011 q
b1111111110111100001100011 H
b1111111110111100001100011 h
b10 F
b10 d
b10010100 E
b10010100 i
b10111011010 /
b10 6
b100000001000 4
b1001 3
b1001 =
b1001 p
b10111011010010010000011 G
b10111011010010010000011 f
b10010000 e
b11011010100010010100 0
b10010100 C
b10010000 D
b10010000 g
b10010000 m
0"
#155
1"
#160
b0 A
b0 q
0B
b10110111101101111011011110110111 H
b10110111101101111011011110110111 h
b0 F
b0 d
b0 a
b0 b
b10011000 E
b10011000 i
b0 >
b0 Q
b0 7
b0 R
b0 I
b0 `
b0 ?
b0 r
b0 @
b0 S
b0 s
1!
0,
b0 1
b0 ;
b0 o
b0 /
b0 6
b0 <
b0 n
b0 4
b0 3
b0 =
b0 p
b1110011 -
b1110011 G
b1110011 f
b10010100 e
b10010100 0
b10011000 C
b10010100 D
b10010100 g
b10010100 m
0"
#165
1"
#170
bx 9
bx P
bx0 a
bx00 b
bx H
bx h
bx I
bx `
bx F
bx d
bx >
bx Q
bx A
bx q
bx 7
bx R
bx E
bx i
x.
xB
b0x00000 8
b0x00000 O
bx ?
bx r
bx @
bx S
bx s
x!
x,
b0xx :
bx 2
bx 5
b0xxxxxxxxxxxx 1
bx ;
bx o
bx /
bx 6
bx <
bx n
bx0 4
bx 3
bx =
bx p
bx -
bx G
bx f
b10011000 e
bx 0
b10011100 C
b10011000 D
b10011000 g
b10011000 m
1#
0"
