template_lab3.v
// Template for Northwestern - CompEng 361 - Lab3 -- Version 1.1
// Groupname: Zach Tey, Matias Ketema
// NetIDs: vcs5888, 

// Some useful defines...please add your own
//General Parameters
   `define WORD_WIDTH 32
   `define NUM_REGS 32
//Opcodes
   `define OPCODE_COMPUTE    7'b0110011
   `define OPCODE_BRANCH     7'b1100011
   `define FUNC_BEQ 3'b000
   `define FUNC_BNE 3'b001
   `define FUNC_BLT 3'b100
   `define FUNC_BGE 3'b101
   `define FUNC_BLTU 3'b110
   `define FUNC_BGEU 3'b111
   `define OPCODE_LOAD       7'b0000011
   `define OPCODE_STORE      7'b0100011 
   `define FUNC_ADD      3'b000
   `define AUX_FUNC_ADD  7'b0000000
   `define AUX_FUNC_SUB  7'b0100000
   `define OPCODE_LUI 7'b0110111
   `define OPCODE_AUIPC 7'b0010111
   `define OPCODE_JAL 7'b1101111 
   `define OPCODE_JALR 7'b1100111 
// idk what there are for yet
   `define SIZE_BYTE  2'b00
   `define SIZE_HWORD 2'b01
   `define SIZE_WORD  2'b10

module SingleCycleCPU(halt, clk, rst);
   output halt;
   input clk, rst;

   wire [`WORD_WIDTH-1:0] PC, InstWord;
   wire [`WORD_WIDTH-1:0] DataAddr, StoreData, DataWord;
   wire [1:0]  MemSize;
   wire        MemWrEn;
   
   wire [4:0]  Rsrc1, Rsrc2, Rdst;
   wire [`WORD_WIDTH-1:0] Rdata1, Rdata2, RWrdata;
   wire        RWrEn;
   wire [19:0] imm_u_type;
   wire [6:0] imm_front_s_type;
   wire [4:0] imm_back_s_type; 
   wire [19:0] imm_i_type;
   wire [31:0] imm_j_type;

   wire [`WORD_WIDTH-1:0] NPC, PC_Plus_4;
   wire [6:0]  opcode;

   wire [6:0]  funct7;
   wire [2:0]  funct3;

   wire invalid_op;
   wire valid_op;
   
   //Inputs/outputs of PC register, MEM, RF; We need to mux them depending on the instruction
   //Don't double drive outputs of mem, reg, ex; They will result in Xs on waveform
   wire [31:0] eu_out;
   wire [6:0] eu_funct7_in;
   wire [31:0] pc_reg_in;

   //Characterize the op-code to its instruction type (R, I, S, U)
   //tbh not sure if this is needed so maybe can delete, but good information to have
   wire [3:0] cur_inst_type;
   parameter R_TYPE = 3'b000;
   parameter I_TYPE = 3'b001;
   parameter S_TYPE = 3'b010;
   parameter U_TYPE = 3'b011;
   parameter B_TYPE = 3'b011;

   //Input Controls to RF, MEM
      //Data
         assign RWrdata = (opcode == `OPCODE_LUI) ? (imm_u_type << 12) :  //lui
                          (opcode == `OPCODE_AUIPC) ? (imm_u_type << 12 + PC) : //auipc 
                          (opcode == `OPCODE_JAL) ? (PC + 4) : 
                          (opcode == `OPCODE_JALR) ? (PC + 4) : 0;              
         assign cur_inst_type = (opcode == `OPCODE_LUI) ? U_TYPE : 0; //not sure if i need this characterization of instruction type
         assign eu_funct7_in = (opcode == `OPCODE_BRANCH && (funct3 == 3'b000 | funct3 == 3'b001)) ? `AUX_FUNC_SUB : 0; //beq, bne

      //Control
         assign RWrEn = (opcode == `OPCODE_LUI) ? 1 : 
                        (opcode == `OPCODE_AUIPC) ? 1 : 
                        (opcode == `OPCODE_JAL) ? 1 : 
                        (opcode == `OPCODE_JALR) ? 1: 0;  
         
   //Halt logic
      // Only support R-TYPE ADD and SUB
   assign halt = !valid_op; //changed this to detect valid_op instead of invalid
   assign invalid_op = !((opcode == `OPCODE_COMPUTE) && (funct3 == `FUNC_ADD) &&
		      ((funct7 == `AUX_FUNC_ADD) || (funct7 == `AUX_FUNC_SUB)));
   assign valid_op = (opcode == `OPCODE_LUI) | (opcode == `OPCODE_AUIPC)|
                     (opcode == `OPCODE_JAL) | (opcode == `OPCODE_JALR) |
                     (opcode == `OPCODE_BRANCH);
     
   // System State 
   Mem   MEM(.InstAddr(PC), .InstOut(InstWord), 
            .DataAddr(DataAddr), .DataSize(MemSize), .DataIn(StoreData), .DataOut(DataWord), .WE(MemWrEn), .CLK(clk));

   RegFile RF(.AddrA(Rsrc1), .DataOutA(Rdata1), 
	      .AddrB(Rsrc2), .DataOutB(Rdata2), 
	      .AddrW(Rdst), .DataInW(RWrdata), .WenW(RWrEn), .CLK(clk));

   Reg PC_REG(.Din(NPC), .Qout(PC), .WE(1'b1), .CLK(clk), .RST(rst));

   // Instruction Decode
   assign opcode = InstWord[6:0];   
   assign Rdst = InstWord[11:7]; 
   assign Rsrc1 = InstWord[19:15]; 
   assign Rsrc2 = InstWord[24:20];
   assign funct3 = InstWord[14:12];  // R-Type, I-Type, S-Type
   assign funct7 = InstWord[31:25];  // R-Type
   assign imm_u_type = InstWord[31:12];
   assign imm_front_s_type = InstWord[32:26];
   assign imm_back_s_type = InstWord[11:7];
   assign imm_i_type = InstWord[31:20]; 
   assign imm_j_type = (opcode == `OPCODE_JALR) ? ((Rdata1 + {{20{InstWord[31]}},InstWord[31:20]}) & 32'hFFFFFFFE) : //jalr
                     (PC + {{11{InstWord[31]}}, InstWord[19:12],InstWord[20], InstWord[30:21],1'b0}); //jal            

   assign MemWrEn = 1'b0; // Change this to allow stores
   //assign RWrEn = 1'b1;  // At the moment every instruction will write to the register file

   // Hardwired to support R-Type instructions -- please add muxes and other control signals
   ExecutionUnit EU(.out(eu_out), .opA(Rdata1), .opB(Rdata2), .func(funct3), .auxFunc(eu_funct7_in));

   // Fetch Address Datapath, notably PC_MEM
   assign PC_Plus_4 = PC + 4;
   assign NPC = ((opcode == `OPCODE_JALR) | (opcode == `OPCODE_JAL)) ? imm_j_type : 
                (opcode == `OPCODE_BRANCH && funct3 == `FUNC_BEQ && eu_out == 0) ? (PC + {InstWord[31] , InstWord [7] , InstWord [30:25] , InstWord [11:8]}) : //beq
                (opcode == `OPCODE_BRANCH && funct3 == `FUNC_BNE && eu_out != 0) ? (PC + {InstWord[31] , InstWord [7] , InstWord [30:25] , InstWord [11:8]}) : PC_Plus_4; //bne
   
endmodule // SingleCycleCPU


// Incomplete version of Lab2 execution unit
// You will need to extend it. Feel free to modify the interface also
module ExecutionUnit(out, opA, opB, func, auxFunc);
   output [`WORD_WIDTH-1:0] out;
   input [`WORD_WIDTH-1:0]  opA, opB;
   input [2:0] 	 func;
   input [6:0] 	 auxFunc;

   // wire [`WORD_WIDTH-1:0] 	 addSub;

   // // Only supports add and subtract
   // assign addSub = (auxFunc == 7'b0100000) ? (opA - opB) : (opA + opB);
   // assign out = (func == 3'b000) ? addSub : 32'hXXXXXXXX;
   
   //Copied over from Zach's Lab 2
   //define operation codes
    localparam OP_ADD = 3'b000; //localparam only exists inside the module
    localparam OP_SUB = 3'b000,
               OP_SLL = 3'b001,
               OP_SLT  = 3'b010,
               OP_SLTU = 3'b011,
               OP_XOR = 3'b100,
               OP_SRL = 3'b101,
               OP_SRA= 3'b101,
               OP_OR = 3'b110,
               OP_AND = 3'b111;
    localparam FUNC_0 = 7'b0000000,
               FUNC_1 = 7'b0100000;

  //Dataflow model
    assign out =
      (func == OP_ADD && auxFunc == FUNC_0) ? (opA + opB) :
      (func == OP_SUB && auxFunc == FUNC_1) ? (opA - opB) :
      (func == OP_SLL && auxFunc == FUNC_0) ? (opA <<  opB[4:0]) :
      (func == OP_SLT && auxFunc == FUNC_0) ? (($signed(opA) <  $signed(opB)) ? 32'd1 : 32'd0) :
      (func == OP_SLTU && auxFunc == FUNC_0) ? ((opA < opB) ? 32'd1 : 32'd0) :
      (func == OP_XOR && auxFunc == FUNC_0) ? (opA ^ opB) :
      (func == OP_SRL && auxFunc == FUNC_0) ? (opA >>  opB[4:0]) :
      (func == OP_SRA && auxFunc == FUNC_1) ? ((opA >> opB[4:0]) | ({32{opA[31]}} << (32 - opB[4:0]))) :
      (func == OP_OR  && auxFunc == FUNC_0) ? (opA | opB) :
      (func == OP_AND && auxFunc == FUNC_0) ? (opA & opB) : 32'b0;

endmodule // ExecutionUnit

lab3_tb.v
// Testbench for Northwestern - CompEng 361 - Lab3 -- Version 1.1
`define CHAR_WIDTH 8
`define MAX_CHAR 80

module tb;
    reg clk, rst;
    reg exit;
    wire halt;
    reg [`CHAR_WIDTH*`MAX_CHAR-1:0] mem_in_fname, mem_out_fname, regs_in_fname, regs_out_fname;
    reg [`CHAR_WIDTH*`MAX_CHAR-1:0] signal_dump_fname;

    // Single Cycle CPU instantiation
    SingleCycleCPU CPU (halt, clk, rst);

    // Clock Period = 10 time units
    always
        #5 clk = ~clk;

    always @(negedge clk)
        if (halt)
            exit = 1;

    initial begin

        // Read commandline options
        if (!$value$plusargs("MEM_IN=%s", mem_in_fname))
            mem_in_fname = "mem_in.hex";
        if (!$value$plusargs("REGS_IN=%s", regs_in_fname))
            regs_in_fname = "regs_in.hex";
        if (!$value$plusargs("REGS_OUT=%s", regs_out_fname))
            regs_out_fname = "regs_out.hex";
        if (!$value$plusargs("MEM_OUT=%s", mem_out_fname))

            mem_out_fname = "mem_out.hex";
         if (!$value$plusargs("DUMP=%s", signal_dump_fname))
            signal_dump_fname = "single.vcd";

        // Clock and reset steup
        #0 rst = 0; exit = 0; clk = 0;
        #0 rst = 1; 
        
        

        // Load program memory and regs
        #0 $readmemh(mem_in_fname, CPU.MEM.Mem);
        #0 $readmemh(regs_in_fname, CPU.RF.Mem);

        // Dumpfile
        $dumpfile(signal_dump_fname);
        $dumpvars();

        // Feel free to modify to inspect whatever you want
        #0 $monitor($time,, "PC=%08x IR=%08x halt=%x exit=%x", CPU.PC, CPU.InstWord, halt, exit);

        // Exit???
        wait(exit);
      
        // Dump memory and regs 
        #0 $writememh(regs_out_fname, CPU.RF.Mem);
        #0 $writememh(mem_out_fname, CPU.MEM.Mem);
        
        $finish;      
   end

endmodule // tb


module Mem(InstAddr, InstOut,
         DataAddr, DataSize, DataIn, DataOut, WE, CLK);
    input [31:0] InstAddr, DataAddr;
    input [1:0] 	DataSize;   
    input [31:0] DataIn;   
    output [31:0] InstOut, DataOut;  
    input      WE, CLK;
    reg [7:0] 	Mem[0:1024];

    wire [31:0] 	DataAddrH, DataAddrW, InstAddrW;

    // Instruction Addresses are word aligned
    assign InstAddrW = InstAddr & 32'hfffffffc;
   
    assign DataAddrH = DataAddr & 32'hfffffffe;
    assign DataAddrW = DataAddr & 32'hfffffffc;

    // Little endian
    assign InstOut = {Mem[InstAddrW+3], Mem[InstAddrW+2], 
		Mem[InstAddrW+1], Mem[InstAddrW]};

    // Little endian
    assign DataOut = (DataSize == 2'b00) ? {4{Mem[DataAddr]}} :
	       ((DataSize == 2'b01) ? {2{Mem[DataAddrH+1],Mem[DataAddrH]}} :
		{Mem[DataAddrW+3], Mem[DataAddrW+2], Mem[DataAddrW+1], Mem[DataAddrW]});
   
     always @ (negedge CLK)
        if (WE) begin
	        case (DataSize)
            2'b00: begin // Write byte
                Mem[DataAddr] <= DataIn[7:0];
            end
            2'b01: begin  // Write halfword
                Mem[DataAddrH] <= DataIn[7:0];
                Mem[DataAddrH+1] <= DataIn[15:8];
            end
            2'b10, 2'b11: begin // Write word
                Mem[DataAddrW] <= DataIn[7:0];
                Mem[DataAddrW+1] <= DataIn[15:8];
                Mem[DataAddrW+2] <= DataIn[23:16];
                Mem[DataAddrW+3] <= DataIn[31:24];
            end
        endcase // case (Size)
     end
endmodule // Mem

module RegFile(AddrA, DataOutA,
	       AddrB, DataOutB,
	       AddrW, DataInW, WenW, CLK);
   input [4:0] AddrA, AddrB, AddrW;
   output [31:0] DataOutA, DataOutB;  
   input [31:0]  DataInW;
   input 	 WenW, CLK;
   reg [31:0] 	 Mem[0:31];
   
   assign DataOutA = (AddrA == 0) ? 32'h00000000 : Mem[AddrA];
   assign DataOutB = (AddrB == 0) ? 32'h00000000 : Mem[AddrB]; 

   always @ (negedge CLK) begin
     if (WenW) begin
       Mem[AddrW] <= DataInW;
     end
      Mem[0] <= 0; // Enforce the invariant that x0 = 0
   end
   
endmodule // RegFile


module Reg(Din, Qout, WE, CLK, RST);
   parameter width = 32;
   parameter init = 0;
   input [width-1:0] Din;
   output [width-1:0] Qout;
   input 	      WE, CLK, RST;

   reg [width-1:0]    Qout;
   
   always @ (negedge CLK or negedge RST)
     if (!RST)
       Qout <= init;
     else
       if (WE)
	     Qout <= Din;
  
endmodule // Reg

single.vcd
$date
	Thu Nov  6 18:55:00 2025
$end
$version
	Icarus Verilog
$end
$timescale
	1s
$end
$scope module tb $end
$var wire 1 ! halt $end
$var reg 1 " clk $end
$var reg 1 # exit $end
$var reg 640 $ mem_in_fname [639:0] $end
$var reg 640 % mem_out_fname [639:0] $end
$var reg 640 & regs_in_fname [639:0] $end
$var reg 640 ' regs_out_fname [639:0] $end
$var reg 1 ( rst $end
$var reg 640 ) signal_dump_fname [639:0] $end
$scope module CPU $end
$var wire 32 * DataAddr [31:0] $end
$var wire 2 + MemSize [1:0] $end
$var wire 1 , MemWrEn $end
$var wire 32 - StoreData [31:0] $end
$var wire 1 " clk $end
$var wire 1 ( rst $end
$var wire 1 . valid_op $end
$var wire 7 / opcode [6:0] $end
$var wire 1 0 invalid_op $end
$var wire 20 1 imm_u_type [19:0] $end
$var wire 32 2 imm_j_type [31:0] $end
$var wire 20 3 imm_i_type [19:0] $end
$var wire 7 4 imm_front_s_type [6:0] $end
$var wire 5 5 imm_back_s_type [4:0] $end
$var wire 1 ! halt $end
$var wire 7 6 funct7 [6:0] $end
$var wire 3 7 funct3 [2:0] $end
$var wire 32 8 eu_out [31:0] $end
$var wire 7 9 eu_funct7_in [6:0] $end
$var wire 4 : cur_inst_type [3:0] $end
$var wire 5 ; Rsrc2 [4:0] $end
$var wire 5 < Rsrc1 [4:0] $end
$var wire 5 = Rdst [4:0] $end
$var wire 32 > Rdata2 [31:0] $end
$var wire 32 ? Rdata1 [31:0] $end
$var wire 32 @ RWrdata [31:0] $end
$var wire 1 A RWrEn $end
$var wire 32 B PC_Plus_4 [31:0] $end
$var wire 32 C PC [31:0] $end
$var wire 32 D NPC [31:0] $end
$var wire 32 E InstWord [31:0] $end
$var wire 32 F DataWord [31:0] $end
$var parameter 3 G B_TYPE $end
$var parameter 3 H I_TYPE $end
$var parameter 3 I R_TYPE $end
$var parameter 3 J S_TYPE $end
$var parameter 3 K U_TYPE $end
$scope module EU $end
$var wire 7 L auxFunc [6:0] $end
$var wire 3 M func [2:0] $end
$var wire 32 N out [31:0] $end
$var wire 32 O opB [31:0] $end
$var wire 32 P opA [31:0] $end
$var parameter 7 Q FUNC_0 $end
$var parameter 7 R FUNC_1 $end
$var parameter 3 S OP_ADD $end
$var parameter 3 T OP_AND $end
$var parameter 3 U OP_OR $end
$var parameter 3 V OP_SLL $end
$var parameter 3 W OP_SLT $end
$var parameter 3 X OP_SLTU $end
$var parameter 3 Y OP_SRA $end
$var parameter 3 Z OP_SRL $end
$var parameter 3 [ OP_SUB $end
$var parameter 3 \ OP_XOR $end
$upscope $end
$scope module MEM $end
$var wire 1 " CLK $end
$var wire 32 ] DataAddr [31:0] $end
$var wire 32 ^ DataAddrH [31:0] $end
$var wire 32 _ DataAddrW [31:0] $end
$var wire 32 ` DataIn [31:0] $end
$var wire 2 a DataSize [1:0] $end
$var wire 32 b InstAddrW [31:0] $end
$var wire 1 , WE $end
$var wire 32 c InstOut [31:0] $end
$var wire 32 d InstAddr [31:0] $end
$var wire 32 e DataOut [31:0] $end
$upscope $end
$scope module PC_REG $end
$var wire 1 " CLK $end
$var wire 32 f Din [31:0] $end
$var wire 1 ( RST $end
$var wire 1 g WE $end
$var parameter 32 h init $end
$var parameter 32 i width $end
$var reg 32 j Qout [31:0] $end
$upscope $end
$scope module RF $end
$var wire 5 k AddrA [4:0] $end
$var wire 5 l AddrB [4:0] $end
$var wire 5 m AddrW [4:0] $end
$var wire 1 " CLK $end
$var wire 32 n DataInW [31:0] $end
$var wire 1 A WenW $end
$var wire 32 o DataOutB [31:0] $end
$var wire 32 p DataOutA [31:0] $end
$upscope $end
$upscope $end
$upscope $end
$enddefinitions $end
$comment Show the parameter values. $end
$dumpall
b100000 i
b0 h
b100 \
b0 [
b101 Z
b101 Y
b11 X
b10 W
b1 V
b110 U
b111 T
b0 S
b100000 R
b0 Q
b11 K
b10 J
b0 I
b1 H
b11 G
$end
#0
$dumpvars
b0 p
b0 o
b10010001101000101000000000000 n
b101 m
b11 l
b1000 k
b0 j
1g
b100 f
bx e
b0 d
b10010001101000101001010110111 c
b0 b
bz a
bz `
bx00 _
bx0 ^
bz ]
b0 P
b0 O
b0 N
b101 M
b0 L
bx F
b10010001101000101001010110111 E
b100 D
b0 C
b100 B
1A
b10010001101000101000000000000 @
b0 ?
b0 >
b101 =
b1000 <
b11 ;
b11 :
b0 9
b0 8
b101 7
b1001 6
b101 5
bx000100 4
b100100011 3
b1000101100100100010 2
b10010001101000101 1
10
b110111 /
1.
bz -
0,
bz +
bz *
b1110011011010010110111001100111011011000110010100101110011101100110001101100100 )
1(
b11100100110010101100111011100110101111101101111011101010111010000101110011010000110010101111000 '
b111001001100101011001110111001101011111011010010110111000101110011010000110010101111000 &
b110110101100101011011010101111101101111011101010111010000101110011010000110010101111000 %
b1101101011001010110110101011111011010010110111000101110011010000110010101111000 $
0#
0"
0!
$end
#5
1"
#10
1A
b0 :
b10000000000000000 @
b10000000000000000 n
b1000 D
b1000 f
bx000000 4
b0 6
b0 3
b0 ;
b0 l
b0 <
b0 k
b1 1
b1 7
b1 M
b1010 5
b1010 =
b1010 m
b10111 /
b1010100010111 E
b1010100010111 c
b100 b
b1000000000100 2
b1000 B
b100 C
b100 d
b100 j
0"
#15
1"
#20
1A
b100000 D
b100000 f
b11000 3
b11000 ;
b11000 l
b1100000000000 1
b0 7
b0 M
b1 5
b1 =
b1 m
b1101111 /
b1100 @
b1100 n
b1100000000000000011101111 E
b1100000000000000011101111 c
b1000 b
b100000 2
b1100 B
b1000 C
b1000 d
b1000 j
0"
#25
1"
#30
1A
b1100 8
b1100 N
b1100 ?
b1100 P
b1100 p
b100100 @
b100100 n
b1100000001000 1
b1 <
b1 k
b10 5
b10 =
b10 m
b1100111 /
b100100 D
b100100 f
b1100000001000000101100111 E
b1100000001000000101100111 c
b100000 b
b100100 2
b100100 B
b100000 C
b100000 d
b100000 j
0"
#35
1"
#40
0A
b11101101110010111011000000000000 8
b11101101110010111011000000000000 N
b101000 D
b101000 f
b100000 9
b100000 L
b0 @
b0 n
b10010001101000101000000000000 >
b10010001101000101000000000000 O
b10010001101000101000000000000 o
b0 ?
b0 P
b0 p
b11000100001001000 2
b1 6
b100101 3
b10010100011000 1
b101 ;
b101 l
b11 <
b11 k
b0 5
b0 =
b0 m
b1100011 /
b10010100011000000001100011 E
b10010100011000000001100011 c
b100100 b
b101000 B
b100100 C
b100100 d
b100100 j
0"
#45
1"
#50
b0 8
b0 N
b0 >
b0 O
b0 o
b111000 D
b111000 f
b100011 3
b11 ;
b11 l
b10001100100000 1
b100 <
b100 k
b10001100100000000001100011 E
b10001100100000000001100011 c
b101000 b
b100000100001001010 2
b101100 B
b101000 C
b101000 d
b101000 j
0"
#55
1"
#60
b1100 >
b1100 O
b1100 o
b100100 ?
b100100 P
b100100 p
b100001 3
b1 ;
b1 l
b10 <
b10 k
b10000100010001 1
b1 7
b1 M
b111100 D
b111100 f
b10000100010001000001100011 E
b10000100010001000001100011 c
b111000 b
b10001100001011000 2
b111100 B
b111000 C
b111000 d
b111000 j
0"
#65
1"
#70
b0 9
b0 L
b0 >
b0 O
b0 o
b0 ?
b0 P
b0 p
1!
0.
b1000000 D
b1000000 f
b0 6
b0 3
b0 ;
b0 l
b0 <
b0 k
b0 1
b0 7
b0 M
b1110011 /
b1110011 E
b1110011 c
b111100 b
b111100 2
b1000000 B
b111100 C
b111100 d
b111100 j
0"
#75
1"
#80
b1000100 D
b1000100 f
b10011 /
b10011 E
b10011 c
b1000000 b
b1000000 2
b1000100 B
b1000000 C
b1000000 d
b1000000 j
1#
0"
