template_lab3.v
// Template for Northwestern - CompEng 361 - Lab3 -- Version 1.1
// Groupname: Zach Tey, Matias Ketema
// NetIDs: vcs5888, 

// Some useful defines...please add your own
//General Parameters
   `define WORD_WIDTH 32
   `define NUM_REGS 32
//Opcodes
   `define OPCODE_COMPUTE    7'b0110011
   `define OPCODE_COMPUTE_IMMEDIATE 7'b0010011
   `define OPCODE_BRANCH     7'b1100011
   `define FUNC_BEQ 3'b000
   `define FUNC_BNE 3'b001
   `define FUNC_BLT 3'b100
   `define FUNC_BGE 3'b101
   `define FUNC_BLTU 3'b110
   `define FUNC_BGEU 3'b111
   `define OPCODE_LOAD       7'b0000011
   `define FUNC_LB 3'b000
   `define FUNC_LH 3'b001
   `define FUNC_LW 3'b010
   `define FUNC_LBU 3'b100
   `define FUNC_LHU 3'b101
   `define OPCODE_STORE      7'b0100011 
   `define FUNC_SB 3'b000
   `define FUNC_SH 3'b001
   `define FUNC_SW 3'b010
   `define FUNC_ADD      3'b000
   `define AUX_FUNC_ADD  7'b0000000
   `define AUX_FUNC_SUB  7'b0100000
   `define AUX_FUNC_M  7'b0000001
   `define OPCODE_LUI 7'b0110111
   `define OPCODE_AUIPC 7'b0010111
   `define OPCODE_JAL 7'b1101111 
   `define OPCODE_JALR 7'b1100111 
// idk what there are for yet
   `define SIZE_BYTE  2'b00
   `define SIZE_HWORD 2'b01
   `define SIZE_WORD  2'b10

module SingleCycleCPU(halt, clk, rst);
   output halt;
   input clk, rst;

   wire [`WORD_WIDTH-1:0] PC, InstWord;
   wire [`WORD_WIDTH-1:0] DataAddr, StoreData, DataWord;
   wire [1:0]  MemSize;
   wire        MemWrEn;
   
   wire [4:0]  Rsrc1, Rsrc2, Rdst;
   wire [`WORD_WIDTH-1:0] Rdata1, Rdata2, RWrdata;
   wire        RWrEn;
   wire [19:0] imm_u_type;
   wire [6:0] imm_front_s_type;
   wire [4:0] imm_back_s_type; 
   wire [19:0] imm_i_type;
   wire [31:0] imm_j_type;
   wire [31:0] imm_b_type;

   wire [`WORD_WIDTH-1:0] NPC, PC_Plus_4;
   wire [6:0]  opcode;

   wire [6:0]  funct7;
   wire [2:0]  funct3;

   wire invalid_op;
   wire valid_op;
   wire memory_alignment_error;

   //Inputs/outputs of PC register, MEM, RF; We need to mux them depending on the instruction
   //Don't double drive outputs of mem, reg, ex; They will result in Xs on waveform
   wire [31:0] eu_out;
   wire [6:0] eu_funct7_in;
   wire [2:0] eu_funct3_in;
   wire [31:0] pc_reg_in;
   wire [31:0] Rdata2_in;
   wire [31:0] StoreData_in;

   //Characterize the op-code to its instruction type (R, I, S, U)
   //tbh not sure if this is needed so maybe can delete, but good information to have
   wire [3:0] cur_inst_type;
   parameter R_TYPE = 3'b000;
   parameter I_TYPE = 3'b001;
   parameter S_TYPE = 3'b010;
   parameter U_TYPE = 3'b011;
   parameter B_TYPE = 3'b011;

   //Input Controls to RF, MEM
      //Data
         assign RWrdata = (opcode == `OPCODE_LUI) ? (imm_u_type << 12) :  //lui
                          (opcode == `OPCODE_AUIPC) ? (imm_u_type << 12 + PC) : //auipc 
                          (opcode == `OPCODE_JAL) ? (PC + 4) : //jal
                          (opcode == `OPCODE_JALR) ? (PC + 4) : //jalr
                          (opcode ==  `OPCODE_LOAD && (funct3 == `FUNC_LB)) ? {{24{DataWord[7]}}, DataWord[7:0]} : //lb
                          (opcode ==  `OPCODE_LOAD && (funct3 == `FUNC_LH)) ? {{16{DataWord[15]}}, DataWord[15:0]} : //lh  
                          (opcode ==  `OPCODE_LOAD && (funct3 == `FUNC_LW)) ? DataWord : //lw  
                          (opcode ==  `OPCODE_LOAD && (funct3 == `FUNC_LBU)) ? {{24{1'b0}}, DataWord[7:0]} : //lbu   
                          (opcode ==  `OPCODE_LOAD && (funct3 == `FUNC_LHU)) ? {{16{1'b0}}, DataWord[15:0]} : //lhu  
                          (opcode ==  `OPCODE_COMPUTE_IMMEDIATE) ? eu_out : //compute_i instructions 
                          (opcode ==  `OPCODE_COMPUTE) ? eu_out : 0; //compute instructions          
         assign cur_inst_type = (opcode == `OPCODE_LUI) ? U_TYPE : 0; //not sure if i need this characterization of instruction type
         assign eu_funct7_in = (opcode == `OPCODE_BRANCH && (funct3 == `FUNC_BEQ | funct3 == `FUNC_BNE)) ? `AUX_FUNC_SUB : //beq, bne 
                               (opcode == `OPCODE_BRANCH && (funct3 == `FUNC_BLT | funct3 == `FUNC_BGE | funct3 == `FUNC_BLTU | funct3 == `FUNC_BGEU)) ? `AUX_FUNC_ADD : funct7; //blt, bge, bltu, bgeu
         assign eu_funct3_in = (opcode == `OPCODE_BRANCH && (funct3 == `FUNC_BNE)) ? 3'b000 : //bne
                               (opcode == `OPCODE_BRANCH && (funct3 == `FUNC_BLT | funct3 == `FUNC_BGE)) ? 3'b010 : //blt, bge
                               (opcode == `OPCODE_BRANCH && (funct3 == `FUNC_BLTU | funct3 == `FUNC_BGEU)) ? 3'b011 : //bltu, bgeu
                               (opcode == `OPCODE_LOAD && (funct3 == `FUNC_LB | funct3 == `FUNC_LH | funct3 == `FUNC_LW | funct3 == `FUNC_LBU | funct3 == `FUNC_LHU)) ? 3'b000: //lb, lh, lw, lbu, lhu 
                               (opcode == `OPCODE_STORE && (funct3 == `FUNC_SB | funct3 == `FUNC_SH | funct3 == `FUNC_SW)) ? 3'b000: funct3; //sb, sh, sw
         assign Rdata2_in = (opcode ==  `OPCODE_LOAD && (funct3 == `FUNC_LB | funct3 == `FUNC_LH | funct3 == `FUNC_LW | funct3 == `FUNC_LBU | funct3 == `FUNC_LHU)) ? {{20{imm_i_type[11]}},imm_i_type} : //lb, lh, lw, lbu, lhu
                            (opcode == `OPCODE_STORE && (funct3 == `FUNC_SB | funct3 == `FUNC_SH | funct3 == `FUNC_SW)) ? {{20{imm_front_s_type[6]}},imm_front_s_type, imm_back_s_type} : //sb, sh, sw
                            (opcode == `OPCODE_COMPUTE_IMMEDIATE) ? {{20{imm_i_type[11]}},imm_i_type} : Rdata2; //compute_i instructions
         assign DataAddr = (opcode ==  `OPCODE_LOAD && (funct3 == `FUNC_LB | funct3 == `FUNC_LH | funct3 == `FUNC_LW | funct3 == `FUNC_LBU | funct3 == `FUNC_LHU)) ? (eu_out) : //lb, lh, lw, lbu, lhu
                           (opcode == `OPCODE_STORE && (funct3 == `FUNC_SB | funct3 == `FUNC_SH | funct3 == `FUNC_SW)) ? eu_out : 0; //sb, sh, sw
         assign MemSize = (opcode ==  `OPCODE_LOAD && (funct3 == `FUNC_LB | funct3 == `FUNC_LBU)) ? 2'b00 : //lb, lbu
                          (opcode ==  `OPCODE_LOAD && (funct3 == `FUNC_LH | funct3 == `FUNC_LHU)) ? 2'b01 : //lh, lhu
                          (opcode ==  `OPCODE_LOAD && (funct3 == `FUNC_LW)) ? 2'b10 : //lw
                          (opcode ==  `OPCODE_STORE && (funct3 == `FUNC_SB)) ? 2'b00 : //lb
                          (opcode ==  `OPCODE_STORE && (funct3 == `FUNC_SH)) ? 2'b01 : //lh
                          (opcode ==  `OPCODE_STORE && (funct3 == `FUNC_SW)) ? 2'b10 : 0; //lw
         assign StoreData_in = (opcode ==  `OPCODE_STORE && (funct3 == `FUNC_SB)) ? {{24{Rdata2[7]}}, Rdata2[7:0]} : //lb
                               (opcode ==  `OPCODE_STORE && (funct3 == `FUNC_SH)) ? {{16{Rdata2[15]}}, Rdata2[15:0]} : //lh
                               (opcode ==  `OPCODE_STORE && (funct3 == `FUNC_SW)) ? Rdata2 : 0; //lw

      //Control
         assign RWrEn = (opcode == `OPCODE_LUI) ? 1 : 
                        (opcode == `OPCODE_AUIPC) ? 1 : 
                        (opcode == `OPCODE_JAL) ? 1 : 
                        (opcode == `OPCODE_JALR) ? 1: 
                        (opcode == `OPCODE_LOAD) ? 1:  
                        (opcode == `OPCODE_COMPUTE_IMMEDIATE) ? 1 :  
                        (opcode == `OPCODE_COMPUTE) ? 1: 0; 
         assign MemWrEn = (opcode == `OPCODE_STORE) ? 1: 0;

         
   //Halt logic
      // Only support R-TYPE ADD and SUB
   assign halt = !valid_op | memory_alignment_error; 
   assign invalid_op = !((opcode == `OPCODE_COMPUTE) && (funct3 == `FUNC_ADD) &&
		      ((funct7 == `AUX_FUNC_ADD) || (funct7 == `AUX_FUNC_SUB)));
   assign valid_op = (opcode == `OPCODE_LUI) | (opcode == `OPCODE_AUIPC)|
                     (opcode == `OPCODE_JAL) | (opcode == `OPCODE_JALR) |
                     (opcode == `OPCODE_BRANCH) | (opcode == `OPCODE_LOAD) |
                     (opcode == `OPCODE_STORE) | (opcode == `OPCODE_COMPUTE_IMMEDIATE) |
                     (opcode == `OPCODE_COMPUTE);
   assign memory_alignment_error = ((((opcode == `OPCODE_LOAD | opcode == `OPCODE_STORE) && (funct3 == `FUNC_LH | funct3 == `FUNC_LHU | funct3 == `FUNC_SH)) && (DataAddr[0] != 1'b0)) ? 1'b1 : 1'b0) | 
                                   ((((opcode == `OPCODE_LOAD | opcode == `OPCODE_STORE) && (funct3 == `FUNC_LW | funct3 == `FUNC_SW)) && (DataAddr[1:0] != 2'b00)) ? 1'b1 : 1'b0);
               
   // System State 
   Mem   MEM(.InstAddr(PC), .InstOut(InstWord), 
            .DataAddr(DataAddr), .DataSize(MemSize), .DataIn(StoreData_in), .DataOut(DataWord), .WE(MemWrEn), .CLK(clk));

   RegFile RF(.AddrA(Rsrc1), .DataOutA(Rdata1), 
	      .AddrB(Rsrc2), .DataOutB(Rdata2), 
	      .AddrW(Rdst), .DataInW(RWrdata), .WenW(RWrEn), .CLK(clk));

   Reg PC_REG(.Din(NPC), .Qout(PC), .WE(1'b1), .CLK(clk), .RST(rst));

   // Instruction Decode
   assign opcode = InstWord[6:0];   
   assign Rdst = InstWord[11:7]; 
   assign Rsrc1 = InstWord[19:15]; 
   assign Rsrc2 = InstWord[24:20];
   assign funct3 = InstWord[14:12];  // R-Type, I-Type, S-Type
   assign funct7 = InstWord[31:25];  // R-Type
   assign imm_u_type = InstWord[31:12];
   assign imm_front_s_type = InstWord[31:25];
   assign imm_back_s_type = InstWord[11:7];
   assign imm_i_type = InstWord[31:20]; 
   assign imm_j_type = (opcode == `OPCODE_JALR) ? ((Rdata1 + {{20{InstWord[31]}},InstWord[31:20]}) & 32'hFFFFFFFE) : //jalr
                     (PC + {{11{InstWord[31]}}, InstWord[19:12],InstWord[20], InstWord[30:21],1'b0}); //jal            
   assign imm_b_type = {{19{InstWord[31]}},   
                        InstWord[31],         
                        InstWord[7],          
                        InstWord[30:25],      
                        InstWord[11:8], 
                        1'b0      
                        };
   //assign MemWrEn = 1'b0; // Change this to allow stores
   //assign RWrEn = 1'b1;  // At the moment every instruction will write to the register file

   // Hardwired to support R-Type instructions -- please add muxes and other control signals
   ExecutionUnit EU(.out(eu_out), .opA(Rdata1), .opB(Rdata2_in), .func(eu_funct3_in), .auxFunc(eu_funct7_in));

   // Fetch Address Datapath, notably PC_MEM
   assign PC_Plus_4 = PC + 4;
   assign NPC = ((opcode == `OPCODE_JALR) | (opcode == `OPCODE_JAL)) ? imm_j_type : //jalr, jal
                (opcode == `OPCODE_BRANCH && funct3 == `FUNC_BEQ && eu_out == 0) ? (PC + imm_b_type) : //beq
                (opcode == `OPCODE_BRANCH && funct3 == `FUNC_BNE && eu_out != 0) ? (PC + imm_b_type) : //bne
                (opcode == `OPCODE_BRANCH && (funct3 == `FUNC_BLT | funct3 == `FUNC_BLTU) && eu_out == 1) ? (PC + imm_b_type) : //blt, bltu
                (opcode == `OPCODE_BRANCH && (funct3 == `FUNC_BGE | funct3 == `FUNC_BGEU) && eu_out == 0) ? (PC + imm_b_type) : PC_Plus_4; //bge, bgeu  
endmodule // SingleCycleCPU


// Incomplete version of Lab2 execution unit
// You will need to extend it. Feel free to modify the interface also
module ExecutionUnit(out, opA, opB, func, auxFunc);
   output [`WORD_WIDTH-1:0] out;
   input [`WORD_WIDTH-1:0]  opA, opB;
   input [2:0] 	 func;
   input [6:0] 	 auxFunc;

   // wire [`WORD_WIDTH-1:0] 	 addSub;

   // // Only supports add and subtract
   // assign addSub = (auxFunc == 7'b0100000) ? (opA - opB) : (opA + opB);
   // assign out = (func == 3'b000) ? addSub : 32'hXXXXXXXX;
   
   //Copied over from Zach's Lab 2
   //define operation codes
    localparam OP_ADD = 3'b000; //localparam only exists inside the module
    localparam OP_SUB = 3'b000,
               OP_SLL = 3'b001,
               OP_SLT  = 3'b010,
               OP_SLTU = 3'b011,
               OP_XOR = 3'b100,
               OP_SRL = 3'b101,
               OP_SRA= 3'b101,
               OP_OR = 3'b110,
               OP_AND = 3'b111,
               OP_MUL = 3'b000,
               OP_MULHSU = 3'b010,
               OP_MULHU= 3'b011,
               OP_DIV = 3'b100,
               OP_DIVU = 3'b101,
               OP_REM = 3'b110,
               OP_REMU = 3'b111;
    localparam FUNC_0 = 7'b0000000,
               FUNC_1 = 7'b0100000,
               FUNC_2 = 7'b0000001;

  //Dataflow model
    assign out =
      (func == OP_ADD && auxFunc == FUNC_0) ? (opA + opB) :
      (func == OP_SUB && auxFunc == FUNC_1) ? (opA - opB) :
      (func == OP_SLL && auxFunc == FUNC_0) ? (opA <<  opB[4:0]) :
      (func == OP_SLT && auxFunc == FUNC_0) ? (($signed(opA) <  $signed(opB)) ? 32'd1 : 32'd0) :
      (func == OP_SLTU && auxFunc == FUNC_0) ? ((opA < opB) ? 32'd1 : 32'd0) :
      (func == OP_XOR && auxFunc == FUNC_0) ? (opA ^ opB) :
      (func == OP_SRL && auxFunc == FUNC_0) ? (opA >>  opB[4:0]) :
      (func == OP_SRA && auxFunc == FUNC_1) ? ((opA >> opB[4:0]) | ({32{opA[31]}} << (32 - opB[4:0]))) :
      (func == OP_OR  && auxFunc == FUNC_0) ? (opA | opB) :
      (func == OP_AND && auxFunc == FUNC_0) ? (opA & opB) :

      (func == OP_MUL && auxFunc == FUNC_2) ? (mul_uu[31:0]) : 
      (func == OP_MULHSU && auxFunc == FUNC_2) ? (mul_su[63:32]) : 
      (func == OP_MULHU && auxFunc == FUNC_2) ? (mul_ss[63:32]) : 
      (func == OP_DIV && auxFunc == FUNC_2) ? div_q_signed : 
      (func == OP_DIVU && auxFunc == FUNC_2) ? div_q_unsigned :
      (func == OP_REM && auxFunc == FUNC_2) ? rem_r_signed :
      (func == OP_REMU && auxFunc == FUNC_2) ? rem_r_unsigned : 32'b0;

   //M-instruction processsing ->
   // 64-bit products for mul variants
   wire signed   [31:0] sA = opA;
   wire signed   [31:0] sB = opB;
   wire         [31:0] uA = opA;
   wire         [31:0] uB = opB;

   wire signed  [63:0] mul_ss  = sA * sB;
   wire signed  [63:0] mul_su  = sA * $signed({1'b0, uB});
   wire         [63:0] mul_uu  = uA * uB;

   wire div_by_zero = (opB == 32'b0);
   wire signed [31:0] div_q_signed = div_by_zero ? 32'hFFFFFFFF :  // DIV: -1
                                     (sA == 32'sh80000000 && sB == 32'hFFFFFFFF) ? 32'sh80000000 : // overflow
                                     sA / sB; //normal division
   wire [31:0] div_q_unsigned = div_by_zero ? 32'hFFFFFFFF : uA / uB;
   wire signed [31:0] rem_r_signed = div_by_zero ? sA : 
                                    (sA == 32'sh80000000 && sB == -32'sd1) ? 32'sd0 :sA % sB;
   wire [31:0] rem_r_unsigned = div_by_zero ? uA : uA % uB;


endmodule // ExecutionUnit

lab3_tb.v
// Testbench for Northwestern - CompEng 361 - Lab3 -- Version 1.1
`define CHAR_WIDTH 8
`define MAX_CHAR 80

module tb;
    reg clk, rst;
    reg exit;
    wire halt;
    reg [`CHAR_WIDTH*`MAX_CHAR-1:0] mem_in_fname, mem_out_fname, regs_in_fname, regs_out_fname;
    reg [`CHAR_WIDTH*`MAX_CHAR-1:0] signal_dump_fname;

    // Single Cycle CPU instantiation
    SingleCycleCPU CPU (halt, clk, rst);

    // Clock Period = 10 time units
    always
        #5 clk = ~clk;

    always @(negedge clk)
        if (halt)
            exit = 1;

    initial begin

        // Read commandline options
        if (!$value$plusargs("MEM_IN=%s", mem_in_fname))
            mem_in_fname = "mem_in.hex";
        if (!$value$plusargs("REGS_IN=%s", regs_in_fname))
            regs_in_fname = "regs_in.hex";
        if (!$value$plusargs("REGS_OUT=%s", regs_out_fname))
            regs_out_fname = "regs_out.hex";
        if (!$value$plusargs("MEM_OUT=%s", mem_out_fname))

            mem_out_fname = "mem_out.hex";
         if (!$value$plusargs("DUMP=%s", signal_dump_fname))
            signal_dump_fname = "single.vcd";

        // Clock and reset steup
        #0 rst = 0; exit = 0; clk = 0;
        #0 rst = 1; 
        
        

        // Load program memory and regs
        #0 $readmemh(mem_in_fname, CPU.MEM.Mem);
        #0 $readmemh(regs_in_fname, CPU.RF.Mem);

        // Dumpfile
        $dumpfile(signal_dump_fname);
        $dumpvars();

        // Feel free to modify to inspect whatever you want
        #0 $monitor($time,, "PC=%08x IR=%08x halt=%x exit=%x", CPU.PC, CPU.InstWord, halt, exit);

        // Exit???
        wait(exit);
      
        // Dump memory and regs 
        #0 $writememh(regs_out_fname, CPU.RF.Mem);
        #0 $writememh(mem_out_fname, CPU.MEM.Mem);
        
        $finish;      
   end

endmodule // tb


module Mem(InstAddr, InstOut,
         DataAddr, DataSize, DataIn, DataOut, WE, CLK);
    input [31:0] InstAddr, DataAddr;
    input [1:0] 	DataSize;   
    input [31:0] DataIn;   
    output [31:0] InstOut, DataOut;  
    input      WE, CLK;
    reg [7:0] 	Mem[0:1024];

    wire [31:0] 	DataAddrH, DataAddrW, InstAddrW;

    // Instruction Addresses are word aligned
    assign InstAddrW = InstAddr & 32'hfffffffc;
   
    assign DataAddrH = DataAddr & 32'hfffffffe;
    assign DataAddrW = DataAddr & 32'hfffffffc;

    // Little endian
    assign InstOut = {Mem[InstAddrW+3], Mem[InstAddrW+2], 
		Mem[InstAddrW+1], Mem[InstAddrW]};

    // Little endian
    assign DataOut = (DataSize == 2'b00) ? {4{Mem[DataAddr]}} :
	       ((DataSize == 2'b01) ? {2{Mem[DataAddrH+1],Mem[DataAddrH]}} :
		{Mem[DataAddrW+3], Mem[DataAddrW+2], Mem[DataAddrW+1], Mem[DataAddrW]});
   
     always @ (negedge CLK)
        if (WE) begin
	        case (DataSize)
            2'b00: begin // Write byte
                Mem[DataAddr] <= DataIn[7:0];
            end
            2'b01: begin  // Write halfword
                Mem[DataAddrH] <= DataIn[7:0];
                Mem[DataAddrH+1] <= DataIn[15:8];
            end
            2'b10, 2'b11: begin // Write word
                Mem[DataAddrW] <= DataIn[7:0];
                Mem[DataAddrW+1] <= DataIn[15:8];
                Mem[DataAddrW+2] <= DataIn[23:16];
                Mem[DataAddrW+3] <= DataIn[31:24];
            end
        endcase // case (Size)
     end
endmodule // Mem

module RegFile(AddrA, DataOutA,
	       AddrB, DataOutB,
	       AddrW, DataInW, WenW, CLK);
   input [4:0] AddrA, AddrB, AddrW;
   output [31:0] DataOutA, DataOutB;  
   input [31:0]  DataInW;
   input 	 WenW, CLK;
   reg [31:0] 	 Mem[0:31];
   
   assign DataOutA = (AddrA == 0) ? 32'h00000000 : Mem[AddrA];
   assign DataOutB = (AddrB == 0) ? 32'h00000000 : Mem[AddrB]; 

   always @ (negedge CLK) begin
     if (WenW) begin
       Mem[AddrW] <= DataInW;
     end
      Mem[0] <= 0; // Enforce the invariant that x0 = 0
   end
   
endmodule // RegFile


module Reg(Din, Qout, WE, CLK, RST);
   parameter width = 32;
   parameter init = 0;
   input [width-1:0] Din;
   output [width-1:0] Qout;
   input 	      WE, CLK, RST;

   reg [width-1:0]    Qout;
   
   always @ (negedge CLK or negedge RST)
     if (!RST)
       Qout <= init;
     else
       if (WE)
	     Qout <= Din;
  
endmodule // Reg

single.vcd
$date
	Sat Nov  8 23:44:20 2025
$end
$version
	Icarus Verilog
$end
$timescale
	1s
$end
$scope module tb $end
$var wire 1 ! halt $end
$var reg 1 " clk $end
$var reg 1 # exit $end
$var reg 640 $ mem_in_fname [639:0] $end
$var reg 640 % mem_out_fname [639:0] $end
$var reg 640 & regs_in_fname [639:0] $end
$var reg 640 ' regs_out_fname [639:0] $end
$var reg 1 ( rst $end
$var reg 640 ) signal_dump_fname [639:0] $end
$scope module CPU $end
$var wire 1 " clk $end
$var wire 1 ! halt $end
$var wire 1 * memory_alignment_error $end
$var wire 1 ( rst $end
$var wire 1 + valid_op $end
$var wire 7 , opcode [6:0] $end
$var wire 1 - invalid_op $end
$var wire 20 . imm_u_type [19:0] $end
$var wire 32 / imm_j_type [31:0] $end
$var wire 20 0 imm_i_type [19:0] $end
$var wire 7 1 imm_front_s_type [6:0] $end
$var wire 5 2 imm_back_s_type [4:0] $end
$var wire 32 3 imm_b_type [31:0] $end
$var wire 7 4 funct7 [6:0] $end
$var wire 3 5 funct3 [2:0] $end
$var wire 32 6 eu_out [31:0] $end
$var wire 7 7 eu_funct7_in [6:0] $end
$var wire 3 8 eu_funct3_in [2:0] $end
$var wire 4 9 cur_inst_type [3:0] $end
$var wire 32 : StoreData_in [31:0] $end
$var wire 5 ; Rsrc2 [4:0] $end
$var wire 5 < Rsrc1 [4:0] $end
$var wire 5 = Rdst [4:0] $end
$var wire 32 > Rdata2_in [31:0] $end
$var wire 32 ? Rdata2 [31:0] $end
$var wire 32 @ Rdata1 [31:0] $end
$var wire 32 A RWrdata [31:0] $end
$var wire 1 B RWrEn $end
$var wire 32 C PC_Plus_4 [31:0] $end
$var wire 32 D PC [31:0] $end
$var wire 32 E NPC [31:0] $end
$var wire 1 F MemWrEn $end
$var wire 2 G MemSize [1:0] $end
$var wire 32 H InstWord [31:0] $end
$var wire 32 I DataWord [31:0] $end
$var wire 32 J DataAddr [31:0] $end
$var parameter 3 K B_TYPE $end
$var parameter 3 L I_TYPE $end
$var parameter 3 M R_TYPE $end
$var parameter 3 N S_TYPE $end
$var parameter 3 O U_TYPE $end
$scope module EU $end
$var wire 7 P auxFunc [6:0] $end
$var wire 3 Q func [2:0] $end
$var wire 32 R opB [31:0] $end
$var wire 32 S sA [31:0] $end
$var wire 32 T sB [31:0] $end
$var wire 32 U uA [31:0] $end
$var wire 32 V uB [31:0] $end
$var wire 32 W rem_r_unsigned [31:0] $end
$var wire 32 X rem_r_signed [31:0] $end
$var wire 32 Y out [31:0] $end
$var wire 32 Z opA [31:0] $end
$var wire 64 [ mul_uu [63:0] $end
$var wire 64 \ mul_su [63:0] $end
$var wire 64 ] mul_ss [63:0] $end
$var wire 32 ^ div_q_unsigned [31:0] $end
$var wire 32 _ div_q_signed [31:0] $end
$var wire 1 ` div_by_zero $end
$var parameter 7 a FUNC_0 $end
$var parameter 7 b FUNC_1 $end
$var parameter 7 c FUNC_2 $end
$var parameter 3 d OP_ADD $end
$var parameter 3 e OP_AND $end
$var parameter 3 f OP_DIV $end
$var parameter 3 g OP_DIVU $end
$var parameter 3 h OP_MUL $end
$var parameter 3 i OP_MULHSU $end
$var parameter 3 j OP_MULHU $end
$var parameter 3 k OP_OR $end
$var parameter 3 l OP_REM $end
$var parameter 3 m OP_REMU $end
$var parameter 3 n OP_SLL $end
$var parameter 3 o OP_SLT $end
$var parameter 3 p OP_SLTU $end
$var parameter 3 q OP_SRA $end
$var parameter 3 r OP_SRL $end
$var parameter 3 s OP_SUB $end
$var parameter 3 t OP_XOR $end
$upscope $end
$scope module MEM $end
$var wire 1 " CLK $end
$var wire 32 u DataAddr [31:0] $end
$var wire 32 v DataAddrH [31:0] $end
$var wire 32 w DataAddrW [31:0] $end
$var wire 32 x DataIn [31:0] $end
$var wire 2 y DataSize [1:0] $end
$var wire 32 z InstAddrW [31:0] $end
$var wire 1 F WE $end
$var wire 32 { InstOut [31:0] $end
$var wire 32 | InstAddr [31:0] $end
$var wire 32 } DataOut [31:0] $end
$upscope $end
$scope module PC_REG $end
$var wire 1 " CLK $end
$var wire 32 ~ Din [31:0] $end
$var wire 1 ( RST $end
$var wire 1 !" WE $end
$var parameter 32 "" init $end
$var parameter 32 #" width $end
$var reg 32 $" Qout [31:0] $end
$upscope $end
$scope module RF $end
$var wire 5 %" AddrA [4:0] $end
$var wire 5 &" AddrB [4:0] $end
$var wire 5 '" AddrW [4:0] $end
$var wire 1 " CLK $end
$var wire 32 (" DataInW [31:0] $end
$var wire 1 B WenW $end
$var wire 32 )" DataOutB [31:0] $end
$var wire 32 *" DataOutA [31:0] $end
$upscope $end
$upscope $end
$upscope $end
$enddefinitions $end
$comment Show the parameter values. $end
$dumpall
b100000 #"
b0 ""
b100 t
b0 s
b101 r
b101 q
b11 p
b10 o
b1 n
b111 m
b110 l
b110 k
b11 j
b10 i
b0 h
b101 g
b100 f
b111 e
b0 d
b1 c
b100000 b
b0 a
b11 O
b10 N
b0 M
b1 L
b11 K
$end
#0
$dumpvars
b0 *"
b0 )"
b10010001101000101000000000000 ("
b101 '"
b11 &"
b1000 %"
b0 $"
1!"
b100 ~
b10110111101101111011011110110111 }
b0 |
b10010001101000101001010110111 {
b0 z
b0 y
b0 x
b0 w
b0 v
b0 u
1`
b11111111111111111111111111111111 _
b11111111111111111111111111111111 ^
b0 ]
b0 \
b0 [
b0 Z
b0 Y
b0 X
b0 W
b0 V
b0 U
b0 T
b0 S
b0 R
b101 Q
b1001 P
b0 J
b10110111101101111011011110110111 I
b10010001101000101001010110111 H
b0 G
0F
b100 E
b0 D
b100 C
1B
b10010001101000101000000000000 A
b0 @
b0 ?
b0 >
b101 =
b1000 <
b11 ;
b0 :
b11 9
b101 8
b1001 7
b0 6
b101 5
b1001 4
b100100100100 3
b101 2
b1001 1
b100100011 0
b1000101100100100010 /
b10010001101000101 .
1-
b110111 ,
1+
0*
b1110011011010010110111001100111011011000110010100101110011101100110001101100100 )
1(
b11100100110010101100111011100110101111101101111011101010111010000101110011010000110010101111000 '
b111001001100101011001110111001101011111011010010110111000101110011010000110010101111000 &
b110110101100101011011010101111101101111011101010111010000101110011010000110010101111000 %
b1101101011001010110110101011111011010010110111000101110011010000110010101111000 $
0#
0"
0!
$end
#5
1"
#10
b1 8
b1 Q
b1000 E
b1000 ~
b0 7
b0 P
1B
b0 9
b10000000000000000 A
b10000000000000000 ("
b0 1
b0 4
b0 0
b0 ;
b0 &"
b0 <
b0 %"
b1 .
b1 5
b1010 3
b1010 2
b1010 =
b1010 '"
b10111 ,
b1010100010111 H
b1010100010111 {
b100 z
b1000000000100 /
b1000 C
b100 D
b100 |
b100 $"
0"
#15
1"
#20
b0 8
b0 Q
1B
b100000 E
b100000 ~
b11000 0
b11000 ;
b11000 &"
b1100000000000 .
b0 5
b100000000000 3
b1 2
b1 =
b1 '"
b1101111 ,
b1100 A
b1100 ("
b1100000000000000011101111 H
b1100000000000000011101111 {
b1000 z
b100000 /
b1100 C
b1000 D
b1000 |
b1000 $"
0"
#25
1"
#30
1B
b1100 6
b1100 Y
b1100 W
b1100 X
b1100 U
b1100 S
b1100 @
b1100 Z
b1100 *"
b100100 A
b100100 ("
b1100000001000 .
b1 <
b1 %"
b10 3
b10 2
b10 =
b10 '"
b1100111 ,
b100100 E
b100100 ~
b1100000001000000101100111 H
b1100000001000000101100111 {
b100000 z
b100100 /
b100100 C
b100000 D
b100000 |
b100000 $"
0"
#35
1"
#40
b0 _
b0 ^
b10010001101000101000000000000 T
b10010001101000101000000000000 V
0`
b10010001101000101000000000000 >
b10010001101000101000000000000 R
0B
b11101101110010111011000000000000 6
b11101101110010111011000000000000 Y
b0 W
b0 X
b101000 E
b101000 ~
b100000 7
b100000 P
b0 A
b0 ("
b10010001101000101000000000000 ?
b10010001101000101000000000000 )"
b0 U
b0 S
b0 @
b0 Z
b0 *"
b11000100001001000 /
b1 1
b1 4
b100101 0
b10010100011000 .
b101 ;
b101 &"
b11 <
b11 %"
b100000 3
b0 2
b0 =
b0 '"
b1100011 ,
b10010100011000000001100011 H
b10010100011000000001100011 {
b100100 z
b101000 C
b100100 D
b100100 |
b100100 $"
0"
#45
1"
#50
b0 6
b0 Y
b11111111111111111111111111111111 _
b11111111111111111111111111111111 ^
b0 T
b0 V
1`
b0 >
b0 R
b1001000 E
b1001000 ~
b0 ?
b0 )"
b100011 0
b11 ;
b11 &"
b10001100100000 .
b100 <
b100 %"
b10001100100000000001100011 H
b10001100100000000001100011 {
b101000 z
b100000100001001010 /
b101100 C
b101000 D
b101000 |
b101000 $"
0"
#55
1"
#60
b11 _
b11 ^
b110110000 ]
b1100 T
b110110000 \
b110110000 [
b1100 V
0`
b1100 >
b1100 R
b10 8
b10 Q
b0 6
b0 Y
b0 7
b0 P
b0 W
b0 X
b1100 ?
b1100 )"
b100100 U
b100100 S
b100100 @
b100100 Z
b100100 *"
b100001 0
b1 ;
b1 &"
b10 <
b10 %"
b10000100010100 .
b100 5
b1001100 E
b1001100 ~
b10000100010100000001100011 H
b10000100010100000001100011 {
b1001000 z
b10100100001101000 /
b1001100 C
b1001000 D
b1001000 |
b1001000 $"
0"
#65
1"
#70
b1 6
b1 Y
b1100 X
b1100 W
b100100 T
b100100 V
b100100 >
b100100 R
b0 _
b1011100 E
b1011100 ~
b0 ^
b100100 ?
b100100 )"
b110110000 [
b1100 U
b110110000 ]
b110110000 \
b1100 S
b1100 @
b1100 Z
b1100 *"
b0 1
b0 4
b10 0
b10 ;
b10 &"
b10000 3
b10000 2
b1000001100 .
b1 <
b1 %"
b10000 =
b10000 '"
b1000001100100001100011 H
b1000001100100001100011 {
b1001100 z
b1100000001001110 /
b1010000 C
b1001100 D
b1001100 |
b1001100 $"
0"
#75
1"
